[{
  "yelping_since": "2014-11-03",
  "useful": 0,
  "compliment_photos": 0,
  "compliment_list": 0,
  "compliment_funny": 0,
  "funny": 0,
  "review_count": 8,
  "friends": ["cvVMmlU1ouS3I5fhutaryQ", "nj6UZ8tdGo8YJ9lUMTVWNw", "RTtdEVhAmeWqCSp0IgJ99w", "t3UKA1sl4e6LY_xsjuvI0A", "s057_BvOfnKNvQquJf7VNg", "VYrdepCgdzJ4WaxP7dBGpg", "XXLSk6sQQDyr3dZ4zE-O0g", "Py8ThfExQaXF2Woqr7kWUw", "233YNvzVtZ1ObkaNkUzNIw", "L6iE9NpmHHJQTk0JQlRlSA", "Y7XTMgZ_q5Bj5f9KhK1R4Q"],
  "fans": 0,
  "compliment_note": 0,
  "compliment_plain": 1,
  "compliment_writer": 0,
  "compliment_cute": 0,
  "average_stars": 4.67,
  "user_id": "oMy_rEb0UBEmMlu-zcxnoQ",
  "compliment_more": 0,
  "elite": [],
  "compliment_hot": 0,
  "cool": 0,
  "name": "Johnny",
  "compliment_profile": 0,
  "compliment_cool": 0
}, {
  "yelping_since": "2013-09-24",
  "useful": 0,
  "compliment_photos": 0,
  "compliment_list": 0,
  "compliment_funny": 0,
  "funny": 0,
  "review_count": 10,
  "friends": ["0njfJmB-7n84DlIgUByCNw", "rFn3Xe3RqHxRSxWOU19Gpg", "HVUAmApa0fCbHHVJ0ALshw", "LBOTb6bJjCdFyDLNswUGmA", "cy3d0moQOsrhWo6VAyA_kA", "XTDeelhFzFX0h_8YELJDIQ", "_erxdUfB8yJA_MCDBAaD_w", "3wMYVoHy15nxOCLZYYIhqA", "74C8Mdn3ISlFIwNZQUPEdg", "Vc980a_kTQL9tzfG1ESq_g", "UPld_8xdzvYmIMA4YxtG0A", "ggppqaSt-4E-Y2XUVv6mMw", "vILp0ctTM3fX0ucJeBw9Hg", "Gl46kwumd4_f102dxgswDw", "i9CDu8j-qcUfZYl67WBwiw", "23lcgZUt6dvtMqV_AZe9KQ", "zacONW61-GjaCF9h5_icgA", "BclKLmGPYlMEVr3OZ_Uuzw", "ol00uKESTC5PR_fETT27AA", "o7e8zecvSlPNTrPi1ZQLzg", "00JBHX0npVAC-itaFOUhpQ", "im3w0wt-ZeE-lDa1zSdyMg", "J_hT3mbtiwHIEWjTBSJnzQ", "_54jmZK9vr9CN-SUSjFbMg", "65w6GtrNNlZDowVDAYGZFQ", "WJeipqBVdQmVhnYrXlLb7A", "vAhyONgVtU-oIaSHRJW0IA", "Soa5S7dQsSjlG3lbTVGb2A", "xtVcWcIKVORcBKhmdbrFiA", "7CghpxENlXnjTGOyNtRDsg", "jI5mX0tNR79J_qoFKZMPdA", "MFtiq9lbm95WVg501wNsww", "SCICexHST-LMCowvH9h7jQ", "SD2VfVLfSkz8m18dvo0HGA", "Y8TLRIPm_ecnZPItgAJ3Kg", "t9bfJI2zvx-3eFrN2zvQnw", "6yUCCifCroUPfXaVo5fCAA", "SGDa-z6MmLmNCamviRsdsA", "aZiDtUBOMHh19IsShZvqJg", "nT9_vJSUk_Tay2Yx84rzCg", "M98bD_uUoC0SJ39keA4OQw", "hT3kGKYFnLflIifxyeKWwg", "loEGz0M-bBf0XnyjrbEvFQ", "Als68VuGzyG3rbn7aLkdBQ", "X1Rx-CRMt3BjtW10xSb3Lw", "svdwrwuL9YHyF3rOgjbB1w", "T0jSTc2uvGtzIHZ843FcHQ", "XAWO5aDTxo-LTE4jVdBdVg", "Q1dLA0wWGO390tH56uKA4Q", "-Ty7mzu-bxd4NmEprFXHEA", "LQKbKXzjGtRRTK6v00o4gg", "BLnaah22WBlLCDwOC7rJ8Q", "IWlU5scMqNaKSWO5ovY_iA", "kMPSklg0XL9uYeYUgX2oCg", "EUH2OBcw32X7wv6Yg4oC_w", "Rkm94t2H5p2aPihBzhqP7w", "MetDJXD8zSj9J5FqTYB_3Q", "TyJ4xokX87KzbNUS8GX85A", "t8H01Z2Vx9GNU8uXVKxr2Q", "gv28x4ugM5FHGI_Jkky4kg", "Y-AnP_QFDcq6B9BoDUUs0A", "PXutYstbsqF3kgj6Tuik7Q", "G0XMrknewP2Y3iHt84qZiA", "gfYOmCKPDni8L3Dd_jibNQ", "M9FL-chYhMA4nZpmTbWIZQ", "zdahkrcKI1Mdj7H0i6oJcQ", "vl3qiO6v4RbFJBpxVREJPw", "RzbEU8OO2wbx67v_005Vlg", "T1LHbOLMsvSjgqAJXQJwxA", "3na1OAZAe44z06SVPY_gPA", "DwOyBVeoiZP7B4ZNkgbVbw", "f-ZbVPvuUIuGGE1cGcTRTQ", "6FmeOxLVL0DVr7KHBC1kVA", "BjN4WYNWk1t8qipjCqMJfA", "7rwANCcxfWgZ7K3LNBcQlw", "1kZ3jeyfPDAq7t7sIb89yg", "TDo7fo6qn8OjokmvyZzPxw", "ZJsUtNX4UXrQNL7ddEegUQ", "J-sGGuafu3SFAWlw5D0xBw"],
  "fans": 0,
  "compliment_note": 0,
  "compliment_plain": 0,
  "compliment_writer": 0,
  "compliment_cute": 0,
  "average_stars": 3.7,
  "user_id": "JJ-aSuM4pCFPdkfoZ34q0Q",
  "compliment_more": 0,
  "elite": [],
  "compliment_hot": 0,
  "cool": 0,
  "name": "Chris",
  "compliment_profile": 0,
  "compliment_cool": 0
}, {
  "yelping_since": "2017-03-02",
  "useful": 0,
  "compliment_photos": 0,
  "compliment_list": 0,
  "compliment_funny": 0,
  "funny": 0,
  "review_count": 1,
  "friends": [],
  "fans": 0,
  "compliment_note": 0,
  "compliment_plain": 0,
  "compliment_writer": 0,
  "compliment_cute": 0,
  "average_stars": 2.0,
  "user_id": "uUzsFQn_6cXDh6rPNGbIFA",
  "compliment_more": 0,
  "elite": [],
  "compliment_hot": 0,
  "cool": 0,
  "name": "Tiffy",
  "compliment_profile": 0,
  "compliment_cool": 0
}, {
  "yelping_since": "2015-03-13",
  "useful": 0,
  "compliment_photos": 0,
  "compliment_list": 0,
  "compliment_funny": 0,
  "funny": 0,
  "review_count": 6,
  "friends": [],
  "fans": 0,
  "compliment_note": 0,
  "compliment_plain": 0,
  "compliment_writer": 0,
  "compliment_cute": 0,
  "average_stars": 4.67,
  "user_id": "mBneaEEH5EMyxaVyqS-72A",
  "compliment_more": 0,
  "elite": [],
  "compliment_hot": 0,
  "cool": 0,
  "name": "Mark",
  "compliment_profile": 0,
  "compliment_cool": 0
}, {
  "yelping_since": "2016-09-08",
  "useful": 0,
  "compliment_photos": 0,
  "compliment_list": 0,
  "compliment_funny": 0,
  "funny": 0,
  "review_count": 3,
  "friends": [],
  "fans": 0,
  "compliment_note": 0,
  "compliment_plain": 0,
  "compliment_writer": 0,
  "compliment_cute": 0,
  "average_stars": 4.67,
  "user_id": "W5mJGs-dcDWRGEhAzUYtoA",
  "compliment_more": 0,
  "elite": [],
  "compliment_hot": 0,
  "cool": 0,
  "name": "Evelyn",
  "compliment_profile": 0,
  "compliment_cool": 0
}, {
  "yelping_since": "2012-07-16",
  "useful": 4,
  "compliment_photos": 0,
  "compliment_list": 0,
  "compliment_funny": 0,
  "funny": 0,
  "review_count": 11,
  "friends": [],
  "fans": 0,
  "compliment_note": 0,
  "compliment_plain": 0,
  "compliment_writer": 1,
  "compliment_cute": 0,
  "average_stars": 3.45,
  "user_id": "4E8--zUZO1Rr1IBK4_83fg",
  "compliment_more": 0,
  "elite": [],
  "compliment_hot": 0,
  "cool": 0,
  "name": "Lisa",
  "compliment_profile": 0,
  "compliment_cool": 0
}, {
  "yelping_since": "2012-05-01",
  "useful": 0,
  "compliment_photos": 0,
  "compliment_list": 0,
  "compliment_funny": 0,
  "funny": 0,
  "review_count": 9,
  "friends": [],
  "fans": 0,
  "compliment_note": 0,
  "compliment_plain": 0,
  "compliment_writer": 0,
  "compliment_cute": 0,
  "average_stars": 4.78,
  "user_id": "Ob-2oGBQ7rwwYwUvhmnf7g",
  "compliment_more": 0,
  "elite": [],
  "compliment_hot": 0,
  "cool": 0,
  "name": "B",
  "compliment_profile": 0,
  "compliment_cool": 0
}, {
  "yelping_since": "2013-03-23",
  "useful": 0,
  "compliment_photos": 0,
  "compliment_list": 0,
  "compliment_funny": 0,
  "funny": 0,
  "review_count": 2,
  "friends": [],
  "fans": 0,
  "compliment_note": 0,
  "compliment_plain": 0,
  "compliment_writer": 0,
  "compliment_cute": 0,
  "average_stars": 5.0,
  "user_id": "JaTVvKsBl0bHHJEpESn4pQ",
  "compliment_more": 0,
  "elite": [],
  "compliment_hot": 0,
  "cool": 0,
  "name": "Peter",
  "compliment_profile": 0,
  "compliment_cool": 0
}, {
  "yelping_since": "2010-10-10",
  "useful": 0,
  "compliment_photos": 0,
  "compliment_list": 0,
  "compliment_funny": 0,
  "funny": 0,
  "review_count": 1,
  "friends": [],
  "fans": 0,
  "compliment_note": 0,
  "compliment_plain": 0,
  "compliment_writer": 0,
  "compliment_cute": 0,
  "average_stars": 1.0,
  "user_id": "Ykj0DVsz0c6rX9ghjd0hDg",
  "compliment_more": 0,
  "elite": [],
  "compliment_hot": 0,
  "cool": 0,
  "name": "Colleen",
  "compliment_profile": 0,
  "compliment_cool": 0
}, {
  "yelping_since": "2012-10-16",
  "useful": 0,
  "compliment_photos": 0,
  "compliment_list": 0,
  "compliment_funny": 0,
  "funny": 0,
  "review_count": 7,
  "friends": [],
  "fans": 0,
  "compliment_note": 0,
  "compliment_plain": 0,
  "compliment_writer": 0,
  "compliment_cute": 0,
  "average_stars": 4.29,
  "user_id": "kmyEPfKnHQJdTceCdoyMQg",
  "compliment_more": 0,
  "elite": [],
  "compliment_hot": 0,
  "cool": 0,
  "name": "A",
  "compliment_profile": 0,
  "compliment_cool": 0
}, {
  "yelping_since": "2010-06-25",
  "useful": 0,
  "compliment_photos": 0,
  "compliment_list": 0,
  "compliment_funny": 0,
  "funny": 0,
  "review_count": 3,
  "friends": [],
  "fans": 0,
  "compliment_note": 0,
  "compliment_plain": 0,
  "compliment_writer": 0,
  "compliment_cute": 0,
  "average_stars": 5.0,
  "user_id": "H54pA7YHfjl8IjhHAfdXJA",
  "compliment_more": 0,
  "elite": [],
  "compliment_hot": 0,
  "cool": 0,
  "name": "Chad",
  "compliment_profile": 0,
  "compliment_cool": 0
}, {
  "yelping_since": "2017-11-29",
  "useful": 0,
  "compliment_photos": 0,
  "compliment_list": 0,
  "compliment_funny": 0,
  "funny": 0,
  "review_count": 1,
  "friends": [],
  "fans": 0,
  "compliment_note": 0,
  "compliment_plain": 0,
  "compliment_writer": 0,
  "compliment_cute": 0,
  "average_stars": 5.0,
  "user_id": "WRae-wZkpRoxMrgJdqwyxg",
  "compliment_more": 0,
  "elite": [],
  "compliment_hot": 0,
  "cool": 0,
  "name": "Mike",
  "compliment_profile": 0,
  "compliment_cool": 0
}, {
  "yelping_since": "2016-06-24",
  "useful": 0,
  "compliment_photos": 0,
  "compliment_list": 0,
  "compliment_funny": 0,
  "funny": 0,
  "review_count": 2,
  "friends": [],
  "fans": 0,
  "compliment_note": 0,
  "compliment_plain": 0,
  "compliment_writer": 0,
  "compliment_cute": 0,
  "average_stars": 1.67,
  "user_id": "Mmv5fPxbF8XEMN4EPT_Khg",
  "compliment_more": 0,
  "elite": [],
  "compliment_hot": 0,
  "cool": 0,
  "name": "Chris",
  "compliment_profile": 0,
  "compliment_cool": 0
}, {
  "yelping_since": "2013-09-29",
  "useful": 3,
  "compliment_photos": 0,
  "compliment_list": 0,
  "compliment_funny": 0,
  "funny": 1,
  "review_count": 1,
  "friends": [],
  "fans": 0,
  "compliment_note": 0,
  "compliment_plain": 0,
  "compliment_writer": 0,
  "compliment_cute": 0,
  "average_stars": 2.0,
  "user_id": "LdqGHXsNQowMrvgTNburJA",
  "compliment_more": 0,
  "elite": [],
  "compliment_hot": 0,
  "cool": 0,
  "name": "Susan",
  "compliment_profile": 0,
  "compliment_cool": 0
}, {
  "yelping_since": "2010-11-28",
  "useful": 0,
  "compliment_photos": 0,
  "compliment_list": 0,
  "compliment_funny": 0,
  "funny": 0,
  "review_count": 4,
  "friends": [],
  "fans": 0,
  "compliment_note": 1,
  "compliment_plain": 0,
  "compliment_writer": 0,
  "compliment_cute": 0,
  "average_stars": 4.0,
  "user_id": "TsgBsn19Wjwpyo81gF9_8Q",
  "compliment_more": 0,
  "elite": [],
  "compliment_hot": 0,
  "cool": 0,
  "name": "Cathy",
  "compliment_profile": 0,
  "compliment_cool": 0
}, {
  "yelping_since": "2017-10-24",
  "useful": 2,
  "compliment_photos": 0,
  "compliment_list": 0,
  "compliment_funny": 0,
  "funny": 0,
  "review_count": 2,
  "friends": [],
  "fans": 0,
  "compliment_note": 0,
  "compliment_plain": 0,
  "compliment_writer": 0,
  "compliment_cute": 0,
  "average_stars": 3.0,
  "user_id": "V--GjQPlTpeWbcB2cS06Gw",
  "compliment_more": 0,
  "elite": [],
  "compliment_hot": 0,
  "cool": 1,
  "name": "Cody",
  "compliment_profile": 0,
  "compliment_cool": 0
}, {
  "yelping_since": "2017-11-07",
  "useful": 0,
  "compliment_photos": 0,
  "compliment_list": 0,
  "compliment_funny": 0,
  "funny": 0,
  "review_count": 1,
  "friends": [],
  "fans": 0,
  "compliment_note": 0,
  "compliment_plain": 0,
  "compliment_writer": 0,
  "compliment_cute": 0,
  "average_stars": 5.0,
  "user_id": "a_gKYQ5YMg39FHNYJLWRHg",
  "compliment_more": 0,
  "elite": [],
  "compliment_hot": 0,
  "cool": 0,
  "name": "Joselyn",
  "compliment_profile": 0,
  "compliment_cool": 0
}, {
  "yelping_since": "2015-06-25",
  "useful": 0,
  "compliment_photos": 0,
  "compliment_list": 0,
  "compliment_funny": 0,
  "funny": 0,
  "review_count": 4,
  "friends": [],
  "fans": 0,
  "compliment_note": 0,
  "compliment_plain": 0,
  "compliment_writer": 0,
  "compliment_cute": 0,
  "average_stars": 3.0,
  "user_id": "sz8Heh56kO_6_LBkoIhNfA",
  "compliment_more": 0,
  "elite": [],
  "compliment_hot": 0,
  "cool": 0,
  "name": "Rosalie",
  "compliment_profile": 0,
  "compliment_cool": 0
}, {
  "yelping_since": "2017-01-07",
  "useful": 0,
  "compliment_photos": 0,
  "compliment_list": 0,
  "compliment_funny": 0,
  "funny": 0,
  "review_count": 3,
  "friends": ["jYiZnueCr7gVq9T34xoa7g", "yFLXGdY6rpHt7hRiwEFMag", "-lMOmerImuxOPZrct6tQ4A", "wlcE7t6C3HrdLLGwoGXJvw", "NSsanvfVcq2GvMyUlQ4FEQ", "fFSUVeacAFV3ygVS5SEjiQ", "NfN97hBP0sg9QjqQ7RuuqA", "3Q6K0gIB2Cn23cIEUBhexA", "KbsDA-3LyFDKA-PbQJeDIA", "_ne-SH5VweelwKE77wMDYA", "iqjcESnZVcsfEog95onL2A", "6ri2PmzKvkyhqq_EJnAeWA", "UiBa715m4gaCWpxIkH7QqQ", "bmiaScI1Lcj2vPYp1TDZuQ", "E239YLEX76286Ybl3PM90Q", "4XuOpVBl6dwCP5dqeF00qg", "-Ko4PiR-QBRsn589gtr31g", "NK2FDJPi8VgmVli6W6fUvg", "Q059bCZKN0qVA2M5B-G0rg", "mvsZOFOb8Ua3tjG7sl_dvQ", "ZxF9MmyHanIUPK4pSkEeNw", "eeyCYQ0BBG86L2-vX3LFCw", "UIte7HAKRi5iKJNdv36kZg", "xc0bgDDzcwOigB55FQltMA", "H9_Z-TRy8IKKpVdqMVHVng", "lrh6a05Ge4T2vCBLUL3_hw", "Up_MxgCGkVS_xZ93_yLs6g", "3hARDDBZcwsllxhql7ytbg", "IfEtrgrmNHnljTYo0vks-w", "QFKBCwyy6XofSS44WpoU2g", "IcIKqLWls7-E7S7MBiMUgA", "Fu0eeWDbT930N_Qs7KyXRw", "TJBvXQqmQgdl2BOkOy0POw", "SP-VWRAEc4OWhfEGRnnP_g", "Il_yq9SaWacthHedNwmxKQ", "bgfu7bly0ULEApOAZjYwFQ", "PGY7tFQffIK4v7otwI9N6Q", "OuaQq4EC26ZpU6DqhN8otA", "DMaQVYVLIsJaEa1VY5D7RQ", "XanpBobPirai3H60LWq1zg", "a4H2W9wfGhZKpMr_DPyflA", "yd4nG5vDBfHhFFgDcQiZEg", "g3w4ybKfuQlAf9lEZHz4fw", "lihzzFkf5jfS05qcRdTaIw", "x-GHfjcCLB5lVoCyr_WM1w", "58N78eOu_RRygUiR6s5Ruw", "Ds4ArclWSyXY0KXUdP_EOg", "IxhAKYxTxdGolO-0JqLUFw", "6UtbIMEpNJK675RUJt_V3Q", "_3mTLZ4WbG_tKq_4oJqYSA", "nMfKEJaWYNyDoy78QHruRA", "EXx8OnME43BxeNoRR51UUQ", "pOMoP7hFJZjYqKp9kr1grQ", "dj6OfxniW2thKkBqOUUNHQ", "n4KahrbPwiUln1u5ZPHHKg", "rY0AvEtrowbmcflHaxnK7A", "O-NUTp0YtlhQOOyDDyr9VA", "lHfu2E3n0sj4uGKOPZQVGQ", "7T3SkiyQII910AouycjlMA", "1zGeUwbM2QyR92bybk281Q", "0TCZ1_7Ekl_CPv8E5RFg5A", "C2p9-bGLb1BLo-okBwbEfg", "XyvNsHmgFSBsvijOTfBBRw", "Po3yksCo9rCKPUUQGMwlVw"],
  "fans": 0,
  "compliment_note": 0,
  "compliment_plain": 0,
  "compliment_writer": 0,
  "compliment_cute": 0,
  "average_stars": 3.33,
  "user_id": "h5ERTYn2vQ1QbjTZvfWPaA",
  "compliment_more": 0,
  "elite": [],
  "compliment_hot": 0,
  "cool": 0,
  "name": "Bobby",
  "compliment_profile": 0,
  "compliment_cool": 0
}, {
  "yelping_since": "2010-07-06",
  "useful": 15,
  "compliment_photos": 0,
  "compliment_list": 0,
  "compliment_funny": 1,
  "funny": 6,
  "review_count": 48,
  "friends": ["hkXekeW_Jj6mIy8r8N7r1Q", "dQDpV-VUtwYGqHznuRV-yw", "Ez7Hve1SaSrCjzl0km5XEA", "DVCo_LH2Etu_aAtI9I6vkA", "XdnOP1pKEzrPcoV-ZXvSxw", "fxvgztSr1DHA869YNGsMtQ", "Vs3bPoc5mWqruxg61-XCsg", "Xs0vCG3OyIKDP6lD2CeWRA", "fU0C1L08LX7FIO8Y3GgWcQ", "Dq4I_hs1mNUA0SyzqwfI_w", "iev9kF-VpBf9BYkPXwNjtQ", "ZT80XHJibHLqiSdfhecYxA", "6Ni3lsxF5syVjTn3Mpxi1g", "q0ol92YKdF7L_-s2g5kfAw", "xD12J7t1DJemC0PnAOZMRw", "WV9-UMmYEq9pvDCbKYuF4A", "ZAJBIWvMdEReTIBaNO2zzw", "gTtJ2w6cFA9UwipW7v6atQ", "YDNK3hTEJSaAfzYubSFPCA", "mPyb1bL-aeaiidA1O1gEiQ", "-Zv99SCrzejB3-Eelvqyfw", "QqZSAYcPWqCEf2hWjFrBVw", "XH5drM54jTK_-fbPLJut9w", "GKsfhVZYb6JGQOQaaHnIdw", "5yLQ3_Ea_qX7mBCkizgZyA", "woHiZYXhcIaDTNRUX5RGUA", "XgvdbQk13DSOp5TUoVPdHQ", "bP37V2AsgKWtdeMRAa9nig", "9O1cTap-XLI5nO-JHj6TxQ", "B5RmV5LhA3R4J0RsyqR70g", "qcIKXuGxhtuEnWLzJoGydA", "srOeMfwyrcwEJbdFdMRrWQ", "iSktH80fgzVLptg9Ep1LiA", "mY5JVfJfQN_yzWEsFU0QGQ", "7sERe-EmH5VMk_NnL8cRFg", "sQ-r-Bs1MEqudkQt3P77BA", "2f6OJCQClEhHrzUb6qExJQ", "VeTGif4-r1auFE4FUOZW7w", "ae6aCtSLDo2ysR1kQLtRaQ", "98W_eoy2FGcz5D2s33Fhkg", "7GRml4yE0k__Gfb6FtTtUg", "qHYQb3-pV1JpqyWcIkkwjQ", "NTLjNHiZuHHGANQ1u2MJyg", "581w9_8Upftg9Htd1-ohKA", "1AWoP8Nhb13k9xxh3W4nVA", "Los1p8wph9TbkU9T0Bo8eQ", "3gbDAW9yeEWsTgbrH0MmXw", "XwyFeLJhhAPvMIOaZ07C7g", "qVA8sxRL6EbAL2C0srCDvg", "gHLqL38fdykytgKH-G3FSw", "88qKciYUsQEmzx8Kw7-FBg", "CV-Pc9io9BgsLhD4aOu9Zg", "uDqTrM55zgyUBPzRVpn8uA", "f8skrxyB4dFKq0-eFYt0og", "BJGigaqQf6Q_KEtBjM29rg", "lc0_H1lq4iFnhKMDmrGpJw", "VwdiLnFD8kG9ZhNY1ITPEA", "4_mipJGGJ2TRy2uAI9SC5A", "93R7AeqerA0b4tuivx-36w", "AwLgRpWdYCM1_JgAze_qsA", "zZoSBcoN5J8FRPf5lKVZww", "25WwoIK8D3L_i63CI2bslQ", "Rxz-K72jZ2yNTV3YI5rjyQ", "62Fq2i4lKCO8ucTFNG370w", "hqMCM9L_L47WCmidyKYGkw", "k5xCuNNwdfpYdsu5PObAOw", "lGMpjdxcbCW5vGi9B2a0Kg", "7v9U0o2do5p0ITFUc_qKNw", "9lWKp5EIovVlCWH1wC7Oeg", "_-XChTHLoOnlxB_cmYPLZg", "bmHmlYJ3kKXdp3_zMXNyrg", "DaxCOBl91VcScCJKK9Gwkw", "nIod29HbvjRPSO4T-va3bQ", "E_EtI0ylBSsGRq-AiRcxkw", "0wXNILLfalmhRVNIVzVVVA", "HDPWfls1uO9fxUGwLndOwg", "u6cO2x5vr6-9EKDCQ0oSMA", "Er6TEjSMmmMD8ipp-kFTEA", "jaOjRguj5zbUyVS_HFIkkw", "Jt4F8KXvz_iBDeuKb7kBHw", "16xi58yj4HLXLRfTaBcadw", "K3ybII2YaLq2fFOvZEFLgA", "Dfg975sbdZa0CFzdl3Ok0w", "hqrU3hLAl46XiYBdbdXang", "6gkcFnXsA9z4IKJTWpylcQ", "oP7sipRK2qEZ9XZnflHh9g", "CTByzVUUHWdsNqFCA3zoAQ", "TIJ5bk0SIoCLqWSQThnx4A", "5INuiPFd6GhQQVWqfrsoHQ", "YwCwGO_lyv7vv2DoqeFjCA", "DvZqzG4MBXhevnI3-X1QMQ", "otYQmnY-MREpT6cb6DYDag", "4SN72FgmpS_yg4rdjmfFzw", "ccB2D20bXGRnEH0G09Y34A", "zpqQv4iOLa9xKOVVHSpl-Q", "medyEUR367ee6vOyCJNQMw", "EtpCxP7RrK2S5K3rQZL3hA", "YLExs45PQ2M6Flmjir3sFQ", "e6iCOIhtupBCiw-VwBvJ4A", "MB7XBiV2Sewriw34xP7Qlg", "xOwAGKMV7OFQYEb46W6OXw", "ulKv4RvqvDRvqbstdY2aQQ", "6mYg8PDu6EJ1vikjKkmj3w", "Y6bVSBO_Ph6KlBU1Oo_J3A", "2p50wcLD1miyLKPOP2xqHQ", "aGsvXWjctthztY68G21OiA", "c1IGa_o7si33CDIv-L6wbw", "KK4d66rvmksrtAkis6XGqw", "ijiskRtiHkSz0aq91g90hw", "n77C6-mAZoKNu9_44ugFEQ", "Gc9mSOvUcA7BrMUh7h7naQ", "1ZIQ2C_EUSTZSyK-APFwvA", "ONtavYgpScFClzuTUVnRXA", "ExuBKYdzYSvnvQE5QwYjZw", "pusUMAm0_Y-oT5Rk93bj2w", "DCek5_94seyPdl4QGtlKmw", "c-kOt8fG1bx-JfYd0GRFFw", "YaQVD-VkxMzhBsW6b-n_Vw", "Ha9LtFuJlvMnE3YTXcHrrA", "tuP1LQoQtTOV_P95Gy9w0A", "3KG84QgF_5lzW1uDMJOghw", "veW3Uy_VjAK4Fmynwh-G_g", "qQnmIgx9utR29rS56Rgq-Q", "i9WwhhIv6dHZsmkmpDVDkA", "MnTGU42t9X8S6wJv05mzlw", "NefCtqzI3t0lnXGz9UDjgQ", "PcvbBOCOcs6_suRDH7TSTg", "d5zRPb1dUGNeoXBxmPY7VA", "sWv6uKChsDtB4s9H3DujQw", "dPYiMpx5AMuI0jeTITGsKg", "wnxS4J6XD3-YrLroQV0Ouw", "jdEXcBMtNYZ_-PzKZnI8qQ", "7D3yq3x-Dv5SbJ3vGIpJsQ", "xz762kpjXUwPajeZCEXbxQ", "PhwfmHJG1LXnddXdK6zbhQ", "7X3lImhKeTfyO0iXgiVUuw", "UOP2bUqlhL9aDSeVRgCjTg", "QIys2vlDprWvWKJp4JBBZQ", "fEgcv6HwG-nkqwr4W7uSiw", "DKnS5_NC9t9Y9ZsLxCiXDQ", "bwZUw2ABFwgztXzPio8yLg", "7nuPhTTp3Bv9X2NLZPsDEw", "5yD_YDdPP_UE28pu_cxbOQ", "jfDzpog_T21NMLac4JO_fA", "mk1TEqWCSMPT100EeXLuiA", "GStb0h5FzizgiWvral-zaQ", "ILA6b9FOlIlZI53N23LXPQ", "q75CUQzdvk2N1YcGL--kKg", "bL1w62zIAt-MOEIpeL30MQ", "QnsGDw5tfM1e7BmGjeplFg", "BWxMCD34Cgef2DR8rJz8Zw", "i28kp8Mx3KAgGYHe8TlsAA", "9J5warf8pd4AIFFjClzyZA", "DtJuu-ezUDi4mP_wdbDGXw", "4ujUS1ZizNFU1N7OewUuNQ", "JGYhs2HTzCRWiIDc4iX37w", "12Nu95iFFE1AayIFIRbWNw", "NwdKv-KBI7OxeWBdpIsfmA", "wLWVT3EMRgYSAWVNynHgJg", "werhtj6NysS7EEoYkwFKsw", "FUuYQyzWRBK7HvOAZ_s1sQ", "dMqLJy8J1a8VpOdcD3bpNw", "1_kItPCk4e-VtYUUg9iiKg", "R16IamdyEKHmjgGeRW_RZA", "itdkCTzLm6eIjEBlz4_Ysw", "RTT4Nua0c18673pt8LHfCA", "OkqWDEqIHYyN7QKSeKiZ8A", "WUTizWBgngFcNdVZwZLYJg", "KedbQJ4Ax1ZhCGG6vaL_mA", "DbH3pEiezWfHJJeqFFN3kg", "HlX9ui1cllC0fSUcsd5rfg", "d30seQvrukI7m_zF6xnB5Q", "kyu8XmdRqOUYCK5BWuvzHw", "gU843PPGS_S5VxS111BPrw", "Jv2YPjBe8MlzneyyRNBX9g", "v3O6ka--Gus4FfJvk4tgeg", "cQKMYxgv1VZ1eanb7RuTOg", "urMngjIG5D8Xde67j3AqSg", "qKaIYWKtFV-HglhyEYHiCw", "keDv6e99O6IjAEVRrQYCXw", "FDuoN8cpcI8y2DBIUoMn4A", "GyerAa1FjB8tzbaYS5DHxw", "rur8m29F4hCIHahcI_hVRg", "SCxM2dAT1vby-eDdOIRcrg", "cgLZMfixIeOMskVT_DG-Vg", "yNgFKgeqZlqa7E7aDVVwug", "MZCtRLrvYVeb67mu_4qmJA", "SeVCpoF59lyhZbS_QgokGg", "nWIbPo8flL2exTGgnq1kFQ", "f4DekkmSsrzG3xsgTZWpNw", "jpRFWQLrPnCQN5FThm7T4w", "6JPLsTTLC_PbpGOok-2vPg", "Gv8de4zfDSlWv5mMX6-5Iw", "3AJ0DM44yZF2wEYsauCzxg", "kKdQq0PAUYhjdeqpYy9DDw", "pY4gYV4MTYjhbRQgVOdgzw", "CnweCjeKquVM69hwD20PiA", "XVVylGn6B-gLcnx33ZinEQ", "50ZW-hlJLS2P8KhPHaUb3A", "AFSZUj0n4Ip7SkR55fqKYA", "_fcNSAsAmUkgBDeNR3HjLQ", "0UorZ4DbUbOHRPYCrBIVuA", "x09u-JslHobIbigUH2embw", "zxyrrMTcg7J5wEjNcMZe-Q", "VvEpuhYDzK2WLB6_fI0wiw", "XEQ-navOBxcqVUG7ECznng", "ctiOS-ctXFT53Qr-urdgSA", "uE2QOkUfhGcS_JaJtTihcw", "2MxSRdhGGE_OFxiwOa6MJg", "MuWbjxrFbRe-Q2XopA9jbg", "CMx6QMkOdISMHauo0_01Kw", "MEFFQMWgY_HwHsiXqneAmg", "H9CDh_DTZuwNwKJ4I2j_PA", "7bcqcIA5AxkuKm3HTZy3KA", "IyRWeRAdNzAW0ElK4mtP4A", "EWLy2zDf23tk9UjVWpM5qA", "dAhoBKucZQRvH32zThaqWw", "kQJCAryAbOfrX0YEfAYdKw", "ESFq49VT1B_17pXuaHjo4g", "qUUZjGCiac1HJ-3sRQlyYA", "aLVSgCZyFKsznVWgWLXIFg", "amzRAQz3Lwmj6DDhSjBTqg", "nuEqfP8cTtNOHpQszmPB4A", "RFp3SokSdMfp4v7H1Xxwyg", "KsejYNlHn-SIRzscyj61bg", "-E5UK5GHbm0wqvzjnelZpQ", "LP883AysBJqOAIzQnIvqnA", "KzM3xWMrKKaUOvT61jMVHA", "ZmEodldPnhcATYZ3_GitYg", "wHUtm6qJigHjaUQ0FMEtXQ", "M-Twq94ErAGBu8sBGFSgjQ", "NYJsOaLwM8M62mGU2093kg", "hNqsXsgJVSi4bDF9ZuB9LA", "yARkJnwiWqQCcj7FJekykA", "y55xsRfi8Nm2GUy_NBXngQ", "wejFVuSYYeMUsjknUEagSQ", "oMtOsVPgFCwlNuoG9ObdpQ", "fHZvRf1M0Yy45eUbph_9qQ", "k7NUYwXyUMOBBdoYCE2fvA", "f5_fgXqDhu-9xvAXUEe2Kw", "DilnrtPdCWQDa-B5_xo76g", "tBtqdCZiP7c05sLGJ9-0IA", "P-u_G_j9nli50KWe0l7pWw", "7tt0GESNpb8e0QzeT8o2TA", "iNh-BlDsk6PkHbcHzZ6_xw", "aRAEXdsdZshvpVFWl7ET5Q", "aKLvRXvvb-3TP6TkC2v4Xw", "8lrJHzUFvya5RZSYFne25A", "aEy43k3P3bLbArVSik2-Gg", "PGKf36-iWwBiUb9SFkBofg", "NTAvra_vBzE_osu-PY2OKQ", "BypPeNocSpIJ6lCN_djPQA", "3zn38b0FhirUpFY6dLGA1Q", "ztaxKl8RcTRyOTMEYbC8JQ", "pbInt8IO-oINljlZAuLGyg", "5NcCIdqOQ1AfylvmT-lqog", "ssUr8Ar5o3lzFvYPmcZnZA", "dMaL9zSAHUYd7cxD2lxveA", "C3gYiouzQCAzVElqzYzmEw", "K6HKJVxXzlwbASNmI61WLA", "UStKXLqnYWVABhdRDMwniA", "Q_dYZNhtGLhMuh-TaOfRew", "bX8zH6DMvwenG4n_2jszsw"],
  "fans": 3,
  "compliment_note": 1,
  "compliment_plain": 1,
  "compliment_writer": 2,
  "compliment_cute": 0,
  "average_stars": 3.73,
  "user_id": "jYnkJR3T8yCERXywoVhWYA",
  "compliment_more": 0,
  "elite": [],
  "compliment_hot": 2,
  "cool": 2,
  "name": "Hugo",
  "compliment_profile": 0,
  "compliment_cool": 1
}, {
  "yelping_since": "2011-08-05",
  "useful": 0,
  "compliment_photos": 0,
  "compliment_list": 0,
  "compliment_funny": 0,
  "funny": 0,
  "review_count": 0,
  "friends": [],
  "fans": 0,
  "compliment_note": 0,
  "compliment_plain": 0,
  "compliment_writer": 0,
  "compliment_cute": 0,
  "average_stars": 4.29,
  "user_id": "GMGZsk1dj043UI3zWgo3cw",
  "compliment_more": 0,
  "elite": [],
  "compliment_hot": 0,
  "cool": 0,
  "name": "volk",
  "compliment_profile": 0,
  "compliment_cool": 0
}, {
  "yelping_since": "2012-09-22",
  "useful": 0,
  "compliment_photos": 0,
  "compliment_list": 0,
  "compliment_funny": 0,
  "funny": 0,
  "review_count": 1,
  "friends": [],
  "fans": 0,
  "compliment_note": 0,
  "compliment_plain": 0,
  "compliment_writer": 0,
  "compliment_cute": 0,
  "average_stars": 5.0,
  "user_id": "eMBV7FugCJq7FIvGhARo2Q",
  "compliment_more": 0,
  "elite": [],
  "compliment_hot": 0,
  "cool": 0,
  "name": "Jack",
  "compliment_profile": 0,
  "compliment_cool": 0
}, {
  "yelping_since": "2017-10-25",
  "useful": 0,
  "compliment_photos": 0,
  "compliment_list": 0,
  "compliment_funny": 0,
  "funny": 0,
  "review_count": 1,
  "friends": [],
  "fans": 0,
  "compliment_note": 0,
  "compliment_plain": 0,
  "compliment_writer": 0,
  "compliment_cute": 0,
  "average_stars": 1.0,
  "user_id": "h5_D5TlEN4bREoy3vR-Vxw",
  "compliment_more": 0,
  "elite": [],
  "compliment_hot": 0,
  "cool": 0,
  "name": "John",
  "compliment_profile": 0,
  "compliment_cool": 0
}, {
  "yelping_since": "2017-12-10",
  "useful": 0,
  "compliment_photos": 0,
  "compliment_list": 0,
  "compliment_funny": 0,
  "funny": 0,
  "review_count": 1,
  "friends": [],
  "fans": 0,
  "compliment_note": 0,
  "compliment_plain": 0,
  "compliment_writer": 0,
  "compliment_cute": 0,
  "average_stars": 1.0,
  "user_id": "bsRNTZ1osSKjuGpHBwX2Pw",
  "compliment_more": 0,
  "elite": [],
  "compliment_hot": 0,
  "cool": 0,
  "name": "Jennifer",
  "compliment_profile": 0,
  "compliment_cool": 0
}, {
  "yelping_since": "2011-03-11",
  "useful": 0,
  "compliment_photos": 0,
  "compliment_list": 0,
  "compliment_funny": 0,
  "funny": 0,
  "review_count": 4,
  "friends": [],
  "fans": 0,
  "compliment_note": 0,
  "compliment_plain": 0,
  "compliment_writer": 0,
  "compliment_cute": 0,
  "average_stars": 5.0,
  "user_id": "8wxTBgvIkCgEZrNfTc1eWQ",
  "compliment_more": 0,
  "elite": [],
  "compliment_hot": 0,
  "cool": 1,
  "name": "mike",
  "compliment_profile": 0,
  "compliment_cool": 0
}, {
  "yelping_since": "2013-07-10",
  "useful": 0,
  "compliment_photos": 0,
  "compliment_list": 0,
  "compliment_funny": 0,
  "funny": 0,
  "review_count": 1,
  "friends": [],
  "fans": 0,
  "compliment_note": 0,
  "compliment_plain": 0,
  "compliment_writer": 0,
  "compliment_cute": 0,
  "average_stars": 5.0,
  "user_id": "moJE85Sfg7Itd3-iIvduQQ",
  "compliment_more": 0,
  "elite": [],
  "compliment_hot": 0,
  "cool": 0,
  "name": "Alan",
  "compliment_profile": 0,
  "compliment_cool": 0
}, {
  "yelping_since": "2016-03-20",
  "useful": 0,
  "compliment_photos": 0,
  "compliment_list": 0,
  "compliment_funny": 0,
  "funny": 0,
  "review_count": 4,
  "friends": [],
  "fans": 0,
  "compliment_note": 0,
  "compliment_plain": 0,
  "compliment_writer": 0,
  "compliment_cute": 0,
  "average_stars": 3.25,
  "user_id": "tkqAUCre66jVB9BbTsZPDA",
  "compliment_more": 0,
  "elite": [],
  "compliment_hot": 0,
  "cool": 0,
  "name": "Hers And",
  "compliment_profile": 0,
  "compliment_cool": 0
}, {
  "yelping_since": "2016-12-06",
  "useful": 1,
  "compliment_photos": 0,
  "compliment_list": 0,
  "compliment_funny": 0,
  "funny": 0,
  "review_count": 1,
  "friends": [],
  "fans": 0,
  "compliment_note": 0,
  "compliment_plain": 0,
  "compliment_writer": 0,
  "compliment_cute": 0,
  "average_stars": 5.0,
  "user_id": "y3ONpOBwpnXb57QNlWUhWQ",
  "compliment_more": 0,
  "elite": [],
  "compliment_hot": 0,
  "cool": 0,
  "name": "Cynthia",
  "compliment_profile": 0,
  "compliment_cool": 0
}, {
  "yelping_since": "2014-11-14",
  "useful": 0,
  "compliment_photos": 0,
  "compliment_list": 0,
  "compliment_funny": 0,
  "funny": 0,
  "review_count": 1,
  "friends": [],
  "fans": 0,
  "compliment_note": 0,
  "compliment_plain": 0,
  "compliment_writer": 0,
  "compliment_cute": 0,
  "average_stars": 5.0,
  "user_id": "PASVfluTGQC5vpjdl-jinw",
  "compliment_more": 0,
  "elite": [],
  "compliment_hot": 0,
  "cool": 0,
  "name": "Brian",
  "compliment_profile": 0,
  "compliment_cool": 0
}, {
  "yelping_since": "2013-12-07",
  "useful": 0,
  "compliment_photos": 0,
  "compliment_list": 0,
  "compliment_funny": 0,
  "funny": 0,
  "review_count": 2,
  "friends": [],
  "fans": 0,
  "compliment_note": 0,
  "compliment_plain": 0,
  "compliment_writer": 0,
  "compliment_cute": 0,
  "average_stars": 5.0,
  "user_id": "bOJZW_hvGkVEIQVwhyqSuw",
  "compliment_more": 0,
  "elite": [],
  "compliment_hot": 0,
  "cool": 0,
  "name": "Justin",
  "compliment_profile": 0,
  "compliment_cool": 0
}, {
  "yelping_since": "2013-08-02",
  "useful": 0,
  "compliment_photos": 0,
  "compliment_list": 0,
  "compliment_funny": 0,
  "funny": 0,
  "review_count": 2,
  "friends": [],
  "fans": 0,
  "compliment_note": 0,
  "compliment_plain": 0,
  "compliment_writer": 0,
  "compliment_cute": 0,
  "average_stars": 2.0,
  "user_id": "LLb4Y_gVVtE38ymLy9gC7g",
  "compliment_more": 0,
  "elite": [],
  "compliment_hot": 0,
  "cool": 0,
  "name": "Lesya",
  "compliment_profile": 0,
  "compliment_cool": 0
}, {
  "yelping_since": "2017-07-30",
  "useful": 1,
  "compliment_photos": 0,
  "compliment_list": 0,
  "compliment_funny": 0,
  "funny": 0,
  "review_count": 1,
  "friends": [],
  "fans": 0,
  "compliment_note": 0,
  "compliment_plain": 0,
  "compliment_writer": 0,
  "compliment_cute": 0,
  "average_stars": 5.0,
  "user_id": "rH53dcL7YKjbztjyA45n0A",
  "compliment_more": 0,
  "elite": [],
  "compliment_hot": 0,
  "cool": 0,
  "name": "Juliana",
  "compliment_profile": 0,
  "compliment_cool": 0
}, {
  "yelping_since": "2014-02-23",
  "useful": 0,
  "compliment_photos": 0,
  "compliment_list": 0,
  "compliment_funny": 0,
  "funny": 0,
  "review_count": 2,
  "friends": [],
  "fans": 0,
  "compliment_note": 0,
  "compliment_plain": 0,
  "compliment_writer": 0,
  "compliment_cute": 0,
  "average_stars": 5.0,
  "user_id": "ddhNJ-nbjwjHoSth6qXJ8g",
  "compliment_more": 0,
  "elite": [],
  "compliment_hot": 0,
  "cool": 0,
  "name": "Ryan",
  "compliment_profile": 0,
  "compliment_cool": 0
}, {
  "yelping_since": "2012-01-13",
  "useful": 0,
  "compliment_photos": 0,
  "compliment_list": 0,
  "compliment_funny": 0,
  "funny": 0,
  "review_count": 7,
  "friends": [],
  "fans": 0,
  "compliment_note": 0,
  "compliment_plain": 0,
  "compliment_writer": 0,
  "compliment_cute": 0,
  "average_stars": 4.57,
  "user_id": "kB2D-z4sHyRsxtim3Qb0mA",
  "compliment_more": 0,
  "elite": [],
  "compliment_hot": 0,
  "cool": 0,
  "name": "Marco",
  "compliment_profile": 0,
  "compliment_cool": 0
}, {
  "yelping_since": "2014-05-27",
  "useful": 0,
  "compliment_photos": 0,
  "compliment_list": 0,
  "compliment_funny": 1,
  "funny": 0,
  "review_count": 13,
  "friends": [],
  "fans": 1,
  "compliment_note": 0,
  "compliment_plain": 2,
  "compliment_writer": 0,
  "compliment_cute": 0,
  "average_stars": 3.46,
  "user_id": "tMNryVdaICS7Vpm5ThNKIA",
  "compliment_more": 0,
  "elite": [],
  "compliment_hot": 0,
  "cool": 0,
  "name": "Alex",
  "compliment_profile": 0,
  "compliment_cool": 1
}, {
  "yelping_since": "2015-03-22",
  "useful": 0,
  "compliment_photos": 0,
  "compliment_list": 0,
  "compliment_funny": 0,
  "funny": 0,
  "review_count": 2,
  "friends": [],
  "fans": 0,
  "compliment_note": 0,
  "compliment_plain": 0,
  "compliment_writer": 0,
  "compliment_cute": 0,
  "average_stars": 3.5,
  "user_id": "WQxXdek5tWFZSPg_GKn1FQ",
  "compliment_more": 0,
  "elite": [],
  "compliment_hot": 0,
  "cool": 0,
  "name": "Dan",
  "compliment_profile": 0,
  "compliment_cool": 0
}, {
  "yelping_since": "2013-12-23",
  "useful": 0,
  "compliment_photos": 0,
  "compliment_list": 0,
  "compliment_funny": 0,
  "funny": 0,
  "review_count": 3,
  "friends": [],
  "fans": 0,
  "compliment_note": 0,
  "compliment_plain": 0,
  "compliment_writer": 0,
  "compliment_cute": 0,
  "average_stars": 1.0,
  "user_id": "u1JFZVeEXBPgEojjy_sI_A",
  "compliment_more": 0,
  "elite": [],
  "compliment_hot": 0,
  "cool": 0,
  "name": "J",
  "compliment_profile": 0,
  "compliment_cool": 0
}, {
  "yelping_since": "2014-10-20",
  "useful": 6,
  "compliment_photos": 0,
  "compliment_list": 0,
  "compliment_funny": 0,
  "funny": 0,
  "review_count": 4,
  "friends": [],
  "fans": 0,
  "compliment_note": 0,
  "compliment_plain": 0,
  "compliment_writer": 0,
  "compliment_cute": 0,
  "average_stars": 2.25,
  "user_id": "gb8PYSCKlvPbMWnqIWXmlQ",
  "compliment_more": 0,
  "elite": [],
  "compliment_hot": 0,
  "cool": 0,
  "name": "Maree",
  "compliment_profile": 0,
  "compliment_cool": 0
}, {
  "yelping_since": "2017-10-25",
  "useful": 0,
  "compliment_photos": 0,
  "compliment_list": 0,
  "compliment_funny": 0,
  "funny": 0,
  "review_count": 1,
  "friends": [],
  "fans": 0,
  "compliment_note": 0,
  "compliment_plain": 0,
  "compliment_writer": 0,
  "compliment_cute": 0,
  "average_stars": 5.0,
  "user_id": "Jbd0A9CTTTzEMvKbZ1BGjw",
  "compliment_more": 0,
  "elite": [],
  "compliment_hot": 0,
  "cool": 0,
  "name": "Nadine",
  "compliment_profile": 0,
  "compliment_cool": 0
}, {
  "yelping_since": "2017-10-19",
  "useful": 0,
  "compliment_photos": 0,
  "compliment_list": 0,
  "compliment_funny": 0,
  "funny": 0,
  "review_count": 1,
  "friends": [],
  "fans": 0,
  "compliment_note": 0,
  "compliment_plain": 0,
  "compliment_writer": 0,
  "compliment_cute": 0,
  "average_stars": 3.0,
  "user_id": "_6Xh4h2EOxAZqzsTsJ_4OA",
  "compliment_more": 0,
  "elite": [],
  "compliment_hot": 0,
  "cool": 0,
  "name": "Carly",
  "compliment_profile": 0,
  "compliment_cool": 0
}, {
  "yelping_since": "2015-06-12",
  "useful": 0,
  "compliment_photos": 0,
  "compliment_list": 0,
  "compliment_funny": 0,
  "funny": 0,
  "review_count": 2,
  "friends": [],
  "fans": 0,
  "compliment_note": 0,
  "compliment_plain": 0,
  "compliment_writer": 0,
  "compliment_cute": 0,
  "average_stars": 3.0,
  "user_id": "akFg3cvYqbihkdYUIjTauQ",
  "compliment_more": 0,
  "elite": [],
  "compliment_hot": 0,
  "cool": 0,
  "name": "Beth",
  "compliment_profile": 0,
  "compliment_cool": 0
}, {
  "yelping_since": "2017-12-11",
  "useful": 0,
  "compliment_photos": 0,
  "compliment_list": 0,
  "compliment_funny": 0,
  "funny": 0,
  "review_count": 1,
  "friends": [],
  "fans": 0,
  "compliment_note": 0,
  "compliment_plain": 0,
  "compliment_writer": 0,
  "compliment_cute": 0,
  "average_stars": 5.0,
  "user_id": "_t6M1XM-4L9XAJ5GBs9Wpw",
  "compliment_more": 0,
  "elite": [],
  "compliment_hot": 0,
  "cool": 0,
  "name": "Ismael",
  "compliment_profile": 0,
  "compliment_cool": 0
}, {
  "yelping_since": "2015-09-21",
  "useful": 0,
  "compliment_photos": 0,
  "compliment_list": 0,
  "compliment_funny": 0,
  "funny": 0,
  "review_count": 1,
  "friends": [],
  "fans": 0,
  "compliment_note": 0,
  "compliment_plain": 0,
  "compliment_writer": 0,
  "compliment_cute": 0,
  "average_stars": 5.0,
  "user_id": "hQMrvOgSxwq56kD9HhStWw",
  "compliment_more": 0,
  "elite": [],
  "compliment_hot": 0,
  "cool": 0,
  "name": "Yuli",
  "compliment_profile": 0,
  "compliment_cool": 0
}, {
  "yelping_since": "2016-11-08",
  "useful": 0,
  "compliment_photos": 0,
  "compliment_list": 0,
  "compliment_funny": 0,
  "funny": 0,
  "review_count": 3,
  "friends": [],
  "fans": 0,
  "compliment_note": 0,
  "compliment_plain": 0,
  "compliment_writer": 0,
  "compliment_cute": 0,
  "average_stars": 4.33,
  "user_id": "qWMB7hzUHO8Bln1rnRhaMw",
  "compliment_more": 0,
  "elite": [],
  "compliment_hot": 0,
  "cool": 0,
  "name": "M",
  "compliment_profile": 0,
  "compliment_cool": 0
}, {
  "yelping_since": "2017-01-13",
  "useful": 0,
  "compliment_photos": 0,
  "compliment_list": 0,
  "compliment_funny": 0,
  "funny": 0,
  "review_count": 1,
  "friends": [],
  "fans": 0,
  "compliment_note": 0,
  "compliment_plain": 0,
  "compliment_writer": 0,
  "compliment_cute": 0,
  "average_stars": 1.0,
  "user_id": "tmi5enLbYFDJCkbfsj7HOA",
  "compliment_more": 0,
  "elite": [],
  "compliment_hot": 0,
  "cool": 0,
  "name": "Kim",
  "compliment_profile": 0,
  "compliment_cool": 0
}, {
  "yelping_since": "2007-08-22",
  "useful": 43,
  "compliment_photos": 0,
  "compliment_list": 0,
  "compliment_funny": 7,
  "funny": 12,
  "review_count": 50,
  "friends": ["HDb4fBWIAQ-foS8qLJty9w", "x0hBZsmBTYxhjjx0MShz1A", "aHKuHxlRDouNwq_PDQPIAA", "HFk-5FLoZZkc1dzp8qD4rQ", "gxI_hk0mBzzF44wvsWpAxw", "V-FDjHqlPqj-q-qd9uqRDw", "zkTqDt3Ja-mPNdnxllasyQ", "iCi4uhijrODJAPqxc8QC1Q", "eW-IQGFyOcqg-aKuhxKf3g", "OKD8L-MfKn4b3x_uI6IM9w", "FkOmPLXOIhb6994LD389Rw", "UeF8hpU2rWEkTrZEXX6cYw", "PFBlZEfuSp9psgeGDcL-Ig", "6yOc1LYPlN9Yyg72eExXDw", "IaWIs4F3CG96s88e75lnsg", "2GTM8JVVA2ieEjoksXwIiw", "YCTe8Tec7xKuoJWNN6f9kw", "FuRswOr4mEEdMemFaBtuhw", "naCaTUmM66M4zBwxTPyuLQ", "9kgj54sYGd0qc5emszjpHA", "OfwexlagAvMI98XXlJ-tKQ", "ee8UZZ46It-IJFLffqR89A", "Jax-6YJH9NNXtfZKfcYtsw", "QrTpRdfzIzzD8SGOifT1fQ", "KSDFmshKwOKgbLwPFnefCw", "LdeIHrRrRKJuWk0lcrgB_Q", "IbakDPisx1lMOVvGAaJLuQ", "taWS4NErfihdenO4J8y8nA", "_5_AH8bJy3ODGLHFQVFj6Q", "7pR0I_uNJTuJiF9TjoZ-CQ", "Jeq6e3dtkxg9mt3vCcIW1A", "gkSVnU359c7Z9T1ZuWos6Q", "ExBHfeqfc9YUCPmjvhqRyQ", "WuqcpisXZH-4raE8j6IkYw", "SFARwTLV-XcJWjjQ-TXoXQ", "RTQlPtMr4zQKo_qvsY61sg", "iQ5EYUb_u7UrIAoy1NDp5g", "XFE4qVTXe-EVR-bXtrM-0w", "xbfFwxIVFLSKAgDZ-JIIuQ", "nnImk681KaRqUVHlSfZjGQ", "TsL6VXZPLzy_S3z_maTuPA", "VPDJt3irJNef_ljoKAaIYQ", "feAyBK3RQa_-EFpynrxckQ", "akatd9YVZm8oxDSZ3rwdsQ", "uAxT_ymDBlvSdnl91xgR6Q", "8c5amuvNyNZtk38FnGLyrg", "ynRkJSonX8Unc5-uk3cw1w", "dk9JnFW1Zyf6Smn6SLPwWQ", "wjdXpIX_8Elcb55bKR3mvg", "hnGyj2H9n7MGDIUrNcu46Q", "3QFTuR5OKc0I-Y6KZKl39g", "LOKBZJtkSb69X0UQ0rr_TA", "ndVIVZy3rp9q9mQnmi1nmg", "WV7qesZApo2P5kwJuXD0_w", "sfWnv6cXmYP0KCw6bvEJKw", "dwHfmDf-UHVqEbLusxD-rw", "-hnNjjn_vwI5z8KpLaivsw", "Uj2OIJk_4I0qKlUYJRPI8w", "RuzCCcrdGRpsRMDc3z7xZQ", "FUDSqooclM_WHlXx0PRugw", "SNyINzzouTZkdETQ62aZsg", "2zYxPvnBEc1bNNVLN-YYBw", "XzkaaiQKSBfEZi0vTdpFJQ", "j_ZwkxKCoV7iGyxxYaAEEg", "FCF3tllSLQCVR1S4whirDA", "wL08KSABN-K4TQzinEMrqw", "Wkw8Tk29rZtPQVwzIhA80A", "-HS0g1mV1ehbljOwT_5iNA", "pe42u7DcCH2QmI81NX-8qA", "I4v9jVVIreY0GvyTPsu3Jg", "uzQxsgonssCSoLwmSkodqg", "07yKZQEADmap1RL-PtJUKQ", "MSHLx8DN5TyBGnGskmasKA", "w9Woq1FIRFc0hv9oAheUQQ", "DGD1unPHR9o_fL_jqdNArQ", "_fXvtI0y3ccxFPCoTt6lSQ", "CSaWfOlprh5G556zxXA04w", "duihVwxxVm8iD1NVPwiWCA", "CpvWdB0N_yDNlzN0byKiCg", "kiSkQ27qVmKcHrusF0nFug", "7ZW5Jd-UBoi6nm7j3oRXTQ", "wlRaWEk-HqF6iCo34k_Vdw", "NmZEdK3ZdlSHHPYfZ-_yQQ", "yHsNSIqPZS38ub1Eo6CA8A", "WJzVPvXn3gC_W8RrItJRqQ", "HySBjJgHEx8eNCmDun5iSg", "_PjEqZApM2u8RpfNhPchhg", "-hpYNkCn-rd5hkyRUzl7CQ", "UTMBLQ7dbvmPIsO8tWe0-Q", "oBjZtEzDiNrVGzsJ_9VUXg", "jFxRKoa3Qciuhdb07eEGVA", "_QEQ5mR-iWETDpBPWUG0bA", "4tJqihMzIOq_xTmwtpxe6g", "gT31WLlMdbcJlHmHbOXT2A", "0YkyaFydLxdrt_l8sf-Xrw", "rbnLpwGyVenDUF0366SbBA", "Q503wfkVgYYRisTYSyWYww", "n4Y6wdh6om3QtIFlWakfDQ", "NoTb8c2eeU2vURulkKFXkg", "FJKkX37OMdgSkWHzrdYoYA"],
  "fans": 1,
  "compliment_note": 9,
  "compliment_plain": 7,
  "compliment_writer": 4,
  "compliment_cute": 0,
  "average_stars": 3.96,
  "user_id": "fV8Yr0c5tFQTQ2SRRJHXHw",
  "compliment_more": 4,
  "elite": [2009],
  "compliment_hot": 2,
  "cool": 5,
  "name": "Michelle",
  "compliment_profile": 0,
  "compliment_cool": 7
}, {
  "yelping_since": "2016-07-31",
  "useful": 0,
  "compliment_photos": 0,
  "compliment_list": 0,
  "compliment_funny": 0,
  "funny": 1,
  "review_count": 3,
  "friends": [],
  "fans": 0,
  "compliment_note": 0,
  "compliment_plain": 0,
  "compliment_writer": 0,
  "compliment_cute": 0,
  "average_stars": 3.67,
  "user_id": "6bHVsO48Xi97pUwduNMoaw",
  "compliment_more": 0,
  "elite": [],
  "compliment_hot": 0,
  "cool": 1,
  "name": "Mazapan",
  "compliment_profile": 0,
  "compliment_cool": 0
}, {
  "yelping_since": "2015-03-31",
  "useful": 2,
  "compliment_photos": 0,
  "compliment_list": 0,
  "compliment_funny": 0,
  "funny": 0,
  "review_count": 3,
  "friends": [],
  "fans": 0,
  "compliment_note": 0,
  "compliment_plain": 0,
  "compliment_writer": 0,
  "compliment_cute": 0,
  "average_stars": 2.0,
  "user_id": "EPvYURBSmAevAWLj47F-4w",
  "compliment_more": 0,
  "elite": [],
  "compliment_hot": 0,
  "cool": 0,
  "name": "Mende",
  "compliment_profile": 0,
  "compliment_cool": 0
}, {
  "yelping_since": "2011-04-25",
  "useful": 0,
  "compliment_photos": 0,
  "compliment_list": 0,
  "compliment_funny": 0,
  "funny": 0,
  "review_count": 1,
  "friends": [],
  "fans": 0,
  "compliment_note": 0,
  "compliment_plain": 0,
  "compliment_writer": 0,
  "compliment_cute": 0,
  "average_stars": 1.0,
  "user_id": "O1DNr2HNo5yiyfQKZ7HRBg",
  "compliment_more": 0,
  "elite": [],
  "compliment_hot": 0,
  "cool": 0,
  "name": "Corey",
  "compliment_profile": 0,
  "compliment_cool": 0
}, {
  "yelping_since": "2015-12-02",
  "useful": 0,
  "compliment_photos": 0,
  "compliment_list": 0,
  "compliment_funny": 0,
  "funny": 0,
  "review_count": 1,
  "friends": [],
  "fans": 0,
  "compliment_note": 0,
  "compliment_plain": 0,
  "compliment_writer": 0,
  "compliment_cute": 0,
  "average_stars": 1.0,
  "user_id": "9kdlTEgDlIjoR1fmTzwI5w",
  "compliment_more": 0,
  "elite": [],
  "compliment_hot": 0,
  "cool": 0,
  "name": "Sofia",
  "compliment_profile": 0,
  "compliment_cool": 0
}, {
  "yelping_since": "2017-11-30",
  "useful": 0,
  "compliment_photos": 0,
  "compliment_list": 0,
  "compliment_funny": 0,
  "funny": 0,
  "review_count": 1,
  "friends": [],
  "fans": 0,
  "compliment_note": 0,
  "compliment_plain": 0,
  "compliment_writer": 0,
  "compliment_cute": 0,
  "average_stars": 5.0,
  "user_id": "L58r9owAlbtELcyFHOZ-jA",
  "compliment_more": 0,
  "elite": [],
  "compliment_hot": 0,
  "cool": 0,
  "name": "Matt",
  "compliment_profile": 0,
  "compliment_cool": 0
}, {
  "yelping_since": "2012-10-18",
  "useful": 0,
  "compliment_photos": 0,
  "compliment_list": 0,
  "compliment_funny": 0,
  "funny": 0,
  "review_count": 1,
  "friends": [],
  "fans": 0,
  "compliment_note": 0,
  "compliment_plain": 0,
  "compliment_writer": 0,
  "compliment_cute": 0,
  "average_stars": 5.0,
  "user_id": "hAZCoaV9rIgJKi0dFiyHlg",
  "compliment_more": 0,
  "elite": [],
  "compliment_hot": 0,
  "cool": 0,
  "name": "Yu Chen",
  "compliment_profile": 0,
  "compliment_cool": 0
}, {
  "yelping_since": "2013-06-23",
  "useful": 0,
  "compliment_photos": 0,
  "compliment_list": 0,
  "compliment_funny": 0,
  "funny": 0,
  "review_count": 2,
  "friends": [],
  "fans": 0,
  "compliment_note": 0,
  "compliment_plain": 0,
  "compliment_writer": 0,
  "compliment_cute": 0,
  "average_stars": 4.5,
  "user_id": "9n2IwcyI3CNxvs1OrKHphA",
  "compliment_more": 0,
  "elite": [],
  "compliment_hot": 0,
  "cool": 0,
  "name": "Kevin",
  "compliment_profile": 0,
  "compliment_cool": 0
}, {
  "yelping_since": "2010-01-06",
  "useful": 0,
  "compliment_photos": 0,
  "compliment_list": 0,
  "compliment_funny": 1,
  "funny": 0,
  "review_count": 62,
  "friends": [],
  "fans": 2,
  "compliment_note": 1,
  "compliment_plain": 0,
  "compliment_writer": 0,
  "compliment_cute": 0,
  "average_stars": 3.3,
  "user_id": "bZkZgll3Fii18x3WRtB5Lg",
  "compliment_more": 1,
  "elite": [],
  "compliment_hot": 0,
  "cool": 0,
  "name": "Dale",
  "compliment_profile": 0,
  "compliment_cool": 1
}, {
  "yelping_since": "2011-10-01",
  "useful": 0,
  "compliment_photos": 0,
  "compliment_list": 0,
  "compliment_funny": 0,
  "funny": 0,
  "review_count": 2,
  "friends": [],
  "fans": 0,
  "compliment_note": 0,
  "compliment_plain": 0,
  "compliment_writer": 0,
  "compliment_cute": 0,
  "average_stars": 5.0,
  "user_id": "4gcu8tVb5ZbXj0AP6ZunOg",
  "compliment_more": 0,
  "elite": [],
  "compliment_hot": 0,
  "cool": 0,
  "name": "Navneet",
  "compliment_profile": 0,
  "compliment_cool": 0
}, {
  "yelping_since": "2017-12-11",
  "useful": 0,
  "compliment_photos": 0,
  "compliment_list": 0,
  "compliment_funny": 0,
  "funny": 0,
  "review_count": 1,
  "friends": [],
  "fans": 0,
  "compliment_note": 0,
  "compliment_plain": 0,
  "compliment_writer": 0,
  "compliment_cute": 0,
  "average_stars": 2.0,
  "user_id": "ow0ZvXgmJgBIc2dgduTtDQ",
  "compliment_more": 0,
  "elite": [],
  "compliment_hot": 0,
  "cool": 0,
  "name": "Adam",
  "compliment_profile": 0,
  "compliment_cool": 0
}, {
  "yelping_since": "2017-11-22",
  "useful": 0,
  "compliment_photos": 0,
  "compliment_list": 0,
  "compliment_funny": 0,
  "funny": 0,
  "review_count": 1,
  "friends": [],
  "fans": 0,
  "compliment_note": 0,
  "compliment_plain": 0,
  "compliment_writer": 0,
  "compliment_cute": 0,
  "average_stars": 5.0,
  "user_id": "y35YADguSrDMGNMZK6r5MQ",
  "compliment_more": 0,
  "elite": [],
  "compliment_hot": 0,
  "cool": 0,
  "name": "Valerie",
  "compliment_profile": 0,
  "compliment_cool": 0
}, {
  "yelping_since": "2015-11-30",
  "useful": 0,
  "compliment_photos": 0,
  "compliment_list": 0,
  "compliment_funny": 0,
  "funny": 0,
  "review_count": 1,
  "friends": [],
  "fans": 0,
  "compliment_note": 0,
  "compliment_plain": 0,
  "compliment_writer": 0,
  "compliment_cute": 0,
  "average_stars": 1.0,
  "user_id": "KWmiBNDFVSvWmU9i0lrlog",
  "compliment_more": 0,
  "elite": [],
  "compliment_hot": 0,
  "cool": 0,
  "name": "Diana",
  "compliment_profile": 0,
  "compliment_cool": 0
}, {
  "yelping_since": "2017-11-21",
  "useful": 1,
  "compliment_photos": 0,
  "compliment_list": 0,
  "compliment_funny": 0,
  "funny": 0,
  "review_count": 2,
  "friends": [],
  "fans": 0,
  "compliment_note": 0,
  "compliment_plain": 0,
  "compliment_writer": 0,
  "compliment_cute": 0,
  "average_stars": 4.0,
  "user_id": "NJhhRGV7jvt2a4JApVw9EA",
  "compliment_more": 0,
  "elite": [],
  "compliment_hot": 0,
  "cool": 0,
  "name": "Shivia",
  "compliment_profile": 0,
  "compliment_cool": 0
}, {
  "yelping_since": "2012-02-08",
  "useful": 12,
  "compliment_photos": 0,
  "compliment_list": 0,
  "compliment_funny": 0,
  "funny": 2,
  "review_count": 13,
  "friends": [],
  "fans": 0,
  "compliment_note": 0,
  "compliment_plain": 0,
  "compliment_writer": 0,
  "compliment_cute": 0,
  "average_stars": 4.0,
  "user_id": "NNUCy-mWCYCROLs1wJRmCQ",
  "compliment_more": 0,
  "elite": [],
  "compliment_hot": 1,
  "cool": 0,
  "name": "Heather",
  "compliment_profile": 0,
  "compliment_cool": 0
}, {
  "yelping_since": "2014-01-06",
  "useful": 1,
  "compliment_photos": 0,
  "compliment_list": 0,
  "compliment_funny": 0,
  "funny": 5,
  "review_count": 2,
  "friends": [],
  "fans": 0,
  "compliment_note": 0,
  "compliment_plain": 0,
  "compliment_writer": 0,
  "compliment_cute": 0,
  "average_stars": 3.5,
  "user_id": "QRKFdoxJSXbN4Ui1a2wttQ",
  "compliment_more": 0,
  "elite": [],
  "compliment_hot": 0,
  "cool": 2,
  "name": "Lee",
  "compliment_profile": 0,
  "compliment_cool": 0
}, {
  "yelping_since": "2016-03-10",
  "useful": 0,
  "compliment_photos": 0,
  "compliment_list": 0,
  "compliment_funny": 0,
  "funny": 0,
  "review_count": 2,
  "friends": [],
  "fans": 0,
  "compliment_note": 0,
  "compliment_plain": 0,
  "compliment_writer": 0,
  "compliment_cute": 0,
  "average_stars": 3.0,
  "user_id": "g3PvxqzdJlaZ-ob7K8sC7g",
  "compliment_more": 0,
  "elite": [],
  "compliment_hot": 0,
  "cool": 0,
  "name": "Shad",
  "compliment_profile": 0,
  "compliment_cool": 0
}, {
  "yelping_since": "2013-01-15",
  "useful": 0,
  "compliment_photos": 0,
  "compliment_list": 0,
  "compliment_funny": 0,
  "funny": 0,
  "review_count": 1,
  "friends": [],
  "fans": 0,
  "compliment_note": 0,
  "compliment_plain": 0,
  "compliment_writer": 0,
  "compliment_cute": 0,
  "average_stars": 5.0,
  "user_id": "kfsHOIsLk2aBj1yHYItx6g",
  "compliment_more": 0,
  "elite": [],
  "compliment_hot": 0,
  "cool": 0,
  "name": "Jen",
  "compliment_profile": 0,
  "compliment_cool": 0
}, {
  "yelping_since": "2015-10-19",
  "useful": 0,
  "compliment_photos": 0,
  "compliment_list": 0,
  "compliment_funny": 0,
  "funny": 0,
  "review_count": 1,
  "friends": [],
  "fans": 0,
  "compliment_note": 0,
  "compliment_plain": 0,
  "compliment_writer": 0,
  "compliment_cute": 0,
  "average_stars": 5.0,
  "user_id": "dGa8T4NqzHCsZhMiYOGktw",
  "compliment_more": 0,
  "elite": [],
  "compliment_hot": 0,
  "cool": 0,
  "name": "Stan",
  "compliment_profile": 0,
  "compliment_cool": 0
}, {
  "yelping_since": "2014-03-18",
  "useful": 1,
  "compliment_photos": 0,
  "compliment_list": 0,
  "compliment_funny": 0,
  "funny": 0,
  "review_count": 1,
  "friends": [],
  "fans": 0,
  "compliment_note": 0,
  "compliment_plain": 0,
  "compliment_writer": 0,
  "compliment_cute": 0,
  "average_stars": 3.0,
  "user_id": "QP0vGv2H8h30ijlI-EkMGg",
  "compliment_more": 0,
  "elite": [],
  "compliment_hot": 0,
  "cool": 1,
  "name": "Dominique",
  "compliment_profile": 0,
  "compliment_cool": 0
}, {
  "yelping_since": "2010-07-09",
  "useful": 0,
  "compliment_photos": 0,
  "compliment_list": 0,
  "compliment_funny": 0,
  "funny": 0,
  "review_count": 4,
  "friends": [],
  "fans": 0,
  "compliment_note": 0,
  "compliment_plain": 0,
  "compliment_writer": 0,
  "compliment_cute": 0,
  "average_stars": 4.0,
  "user_id": "AUeeFb-1kN-ssfb39FJIBA",
  "compliment_more": 0,
  "elite": [],
  "compliment_hot": 0,
  "cool": 0,
  "name": "eula",
  "compliment_profile": 0,
  "compliment_cool": 0
}, {
  "yelping_since": "2017-10-30",
  "useful": 0,
  "compliment_photos": 0,
  "compliment_list": 0,
  "compliment_funny": 0,
  "funny": 0,
  "review_count": 1,
  "friends": [],
  "fans": 0,
  "compliment_note": 0,
  "compliment_plain": 0,
  "compliment_writer": 0,
  "compliment_cute": 0,
  "average_stars": 5.0,
  "user_id": "mWeIs5leEHuM2m6uHET32w",
  "compliment_more": 0,
  "elite": [],
  "compliment_hot": 0,
  "cool": 0,
  "name": "Bryan",
  "compliment_profile": 0,
  "compliment_cool": 0
}, {
  "yelping_since": "2015-05-18",
  "useful": 5,
  "compliment_photos": 0,
  "compliment_list": 0,
  "compliment_funny": 0,
  "funny": 2,
  "review_count": 4,
  "friends": [],
  "fans": 0,
  "compliment_note": 1,
  "compliment_plain": 1,
  "compliment_writer": 0,
  "compliment_cute": 0,
  "average_stars": 2.0,
  "user_id": "1iIebpwPVifig9Xi0EI8Dg",
  "compliment_more": 0,
  "elite": [],
  "compliment_hot": 0,
  "cool": 0,
  "name": "Ella",
  "compliment_profile": 0,
  "compliment_cool": 0
}, {
  "yelping_since": "2013-06-23",
  "useful": 0,
  "compliment_photos": 0,
  "compliment_list": 0,
  "compliment_funny": 0,
  "funny": 0,
  "review_count": 9,
  "friends": [],
  "fans": 0,
  "compliment_note": 0,
  "compliment_plain": 0,
  "compliment_writer": 0,
  "compliment_cute": 0,
  "average_stars": 1.3,
  "user_id": "_P215TQRt2RlnoN9jLGygg",
  "compliment_more": 0,
  "elite": [],
  "compliment_hot": 0,
  "cool": 0,
  "name": "Masha",
  "compliment_profile": 0,
  "compliment_cool": 0
}, {
  "yelping_since": "2013-10-26",
  "useful": 0,
  "compliment_photos": 0,
  "compliment_list": 0,
  "compliment_funny": 0,
  "funny": 0,
  "review_count": 6,
  "friends": [],
  "fans": 0,
  "compliment_note": 0,
  "compliment_plain": 0,
  "compliment_writer": 0,
  "compliment_cute": 0,
  "average_stars": 3.33,
  "user_id": "hic9wcuQuqa3yXdf34qfbg",
  "compliment_more": 0,
  "elite": [],
  "compliment_hot": 0,
  "cool": 0,
  "name": "Preston",
  "compliment_profile": 0,
  "compliment_cool": 0
}, {
  "yelping_since": "2017-11-14",
  "useful": 4,
  "compliment_photos": 0,
  "compliment_list": 0,
  "compliment_funny": 0,
  "funny": 0,
  "review_count": 5,
  "friends": [],
  "fans": 0,
  "compliment_note": 0,
  "compliment_plain": 0,
  "compliment_writer": 0,
  "compliment_cute": 0,
  "average_stars": 4.2,
  "user_id": "jPbLyRJWygYEbA-FWMx3Gw",
  "compliment_more": 0,
  "elite": [],
  "compliment_hot": 0,
  "cool": 0,
  "name": "Cathy",
  "compliment_profile": 0,
  "compliment_cool": 0
}, {
  "yelping_since": "2015-05-13",
  "useful": 1,
  "compliment_photos": 0,
  "compliment_list": 0,
  "compliment_funny": 0,
  "funny": 0,
  "review_count": 6,
  "friends": [],
  "fans": 0,
  "compliment_note": 0,
  "compliment_plain": 0,
  "compliment_writer": 0,
  "compliment_cute": 0,
  "average_stars": 4.0,
  "user_id": "pE08CrioZMP7bhmzgZkDGw",
  "compliment_more": 0,
  "elite": [],
  "compliment_hot": 0,
  "cool": 0,
  "name": "Stephanie",
  "compliment_profile": 0,
  "compliment_cool": 0
}, {
  "yelping_since": "2017-03-28",
  "useful": 0,
  "compliment_photos": 0,
  "compliment_list": 0,
  "compliment_funny": 0,
  "funny": 0,
  "review_count": 1,
  "friends": [],
  "fans": 0,
  "compliment_note": 0,
  "compliment_plain": 0,
  "compliment_writer": 0,
  "compliment_cute": 0,
  "average_stars": 5.0,
  "user_id": "OZKh_VLIhh_tL5r3Lr-EtA",
  "compliment_more": 0,
  "elite": [],
  "compliment_hot": 0,
  "cool": 0,
  "name": "Lexi",
  "compliment_profile": 0,
  "compliment_cool": 0
}, {
  "yelping_since": "2013-02-27",
  "useful": 0,
  "compliment_photos": 0,
  "compliment_list": 0,
  "compliment_funny": 0,
  "funny": 0,
  "review_count": 8,
  "friends": [],
  "fans": 1,
  "compliment_note": 0,
  "compliment_plain": 0,
  "compliment_writer": 0,
  "compliment_cute": 0,
  "average_stars": 5.0,
  "user_id": "R_jGXfWM2OT1cCVTMMH-jw",
  "compliment_more": 0,
  "elite": [],
  "compliment_hot": 0,
  "cool": 0,
  "name": "Am",
  "compliment_profile": 0,
  "compliment_cool": 0
}, {
  "yelping_since": "2011-06-05",
  "useful": 45,
  "compliment_photos": 0,
  "compliment_list": 0,
  "compliment_funny": 0,
  "funny": 0,
  "review_count": 19,
  "friends": [],
  "fans": 0,
  "compliment_note": 0,
  "compliment_plain": 0,
  "compliment_writer": 0,
  "compliment_cute": 0,
  "average_stars": 4.26,
  "user_id": "gkMSWgpoBcc96JqhMFbKJg",
  "compliment_more": 0,
  "elite": [],
  "compliment_hot": 0,
  "cool": 1,
  "name": "Laura",
  "compliment_profile": 0,
  "compliment_cool": 0
}, {
  "yelping_since": "2008-09-23",
  "useful": 174,
  "compliment_photos": 1,
  "compliment_list": 0,
  "compliment_funny": 47,
  "funny": 151,
  "review_count": 762,
  "friends": ["Cit5yho-DqotA0BnXHErTQ", "bm2DqfP4P454FjEtCbZdkQ", "xruy2cNpgz-x98-ACE_Q_A", "Y6AnR_5l_RgdSM-GDsqRgA", "1Ky883b87muXYlzlBpepgg", "uNLaGbgcfaN4vlFyse9j5g", "ImipV7VpdxeM7ucEnLvqjg", "w16hgQetwgAllUNr10P9Kg", "gejGrDsdw79VOJWMKp9Cbg", "fmhTUB0WsfYXZg_Atz8bSQ", "-RRimFSipVOZ-xfQEPvLzw", "TdT1NWvONMaLjnxwYbeZHg", "gC9yxjFC7eN1kN0xU-ryqw", "EtBea-v-2JAvZdfg7XH7iA", "m1p_9QzkD899UbJBw8eJjQ", "Wd3mZ6A7kir0gVjhVRjTnA", "9A0BjnrnYdEg4uRgfFhppw", "S5sRpKBshe-Mrs1UL2KurQ", "ZQkaeEO7emlU21q0KqEPBQ", "Ed1z7VbBWWkwwZhY_KJOFw", "6ZR7HuUpHk_NQNs0dT0oLg", "dE9YaRaUtkDm-xJrW3BSPg", "gjQ00L18PvAV450ZOfqYng", "3FFjZg2Klrp8ORbCNOYQWA", "e4CCD4D7iA4SCxryHNtzUQ", "FLgpXs98f_Qe9AJW0oLSfg", "2XDS3CqfNwgNuKAZKag-sw", "3Kt2LoQVTfJ0raDTV9aF8Q", "qnaEvCbs9SmLu852A22RWg", "cPcStFGBlk-6lWWsttIfVQ", "8_tiZTl5tSkZOfQ7K2K1FQ", "Dd468V-ocBrbINHBNpBbiQ", "henDqMyd5F1K6jBnHTrYqQ", "buVMZSmWLwC0TF7-5zYAAA", "_yaKBcvNQN-_T4IC9cTg_A", "7wS68ArAYnc7BY2DGxaLLQ", "OZRhAe-La1bX2xhLGJujVg", "Y_tPAU6E4kMd9bXroGGaKg", "suVuMvaGfRAfEtncIKx2GQ", "ZuqRUfg4KLF9H4PYHFUS2w", "_pMzR6yoPbU98t-NH8TZ3w", "-SgfRZ2Yd6bmE4q6EAu7CA", "4kUPaQE3H71TsOqxJpzxdA", "6jkxmmbYsUXc5dRyEBh4lg", "ppQpZMPEiPaaEasMy8Wf4w", "1oywhk9P-Dvh1slY23GsbA", "MUJ44YhlZ69KjiLZfYt6Lg", "pecYyVMjqMxawD7Xz-t1jw", "RkW6MCmc9NJliGsTo40CeA", "KJXtd4CnD6trhlVRTJW4RA", "b1yKGpLFa5FzNY41FKurbQ", "Y3_BasfNNDLDGu4f2JPpvg", "DYZ9B5sR4LyGXU0KHLNdHQ", "ZdY3VTgSHaLgCfnRZEeosQ", "gExQu9hMZD0lD9WC58omTQ", "U-pkHFC07TLfMRq2HbQTtQ", "XDHpi1Za6Ti_qOs_X8vM8g", "QQ9TxdWsOxPcTfySVuQLjw", "aTp1P-hgpI1bXnS-nN0bKw", "GR0LcIIaPpqyMH5MCpPJJA", "aOvHvpBxzHz60nZpcQymJA", "Wd43YdZtztC169e2K_7jog", "VcT_64wY1yb91Vfu4asqvw", "4n0eMAeCSvWRl6an5Z8OGg", "CYQNdjHCL9nedkLMfKLHmg", "DAU63VKPCPwjlxqUJi0mEg", "7cDAEEnwfSqG2Lv8Vanr3Q", "d06Bj6YnQz0OThgaaLRdRQ", "FrjgkqEMhFeAkBxjD_Lx5g", "KRoCu_g3tiXhJANzo1J57A", "uCpoTqScJg15LKIDXenbIA", "oaEISy8gzI8KFmbY0cVmNQ", "EltaWmMEXEzvKbmGMZ1FKA", "0uPeuk27jdw2UGqbMSWe-Q", "9r-WEZ3pd9Ue_mgPczbZ7w", "sTj6cTG9xClrBhQNn8qJRA", "x1paA3aUHJTurbtFkBSOGg", "TMEg_Srg5VmWd4YbEVyqTQ", "0cZaLvThOfuQa9spTMyv8g", "OXYtOFX9xXukagW5Ku5dfg", "5Ftb40mmwptuN-QGBfGXbA", "OOJe5AlI3O7MAMqPEJpZWQ", "mnrDsvKj1LfyNr5pxzzUmg", "1wEWs-el7eauwbdbxGZk8Q", "JwQ8oI5iXKaqfBgZSpm19Q", "GkkXSqLoNnbTduSuYlz-oA", "ygH3Bp6MZOkY-WBStnpkRg", "tlWur9j2k5gpmuY91D5t6Q", "Z5T4VAwlVBSir0eAuUKaVQ", "I2-XmIv-IjmCpjMJ6uwY1A", "8VJnUeQh8RRhNtbbPECaLw", "TV5KY6-zSqyXnDKx2juIeA", "Bw18f_vUTzL_GhI5YkkeSQ", "tW8TT4KXyix0i0VA6jsI9g", "MKgpIiuzs752BJjPeCW0cw", "PJUIB97YoA6iF6-HHQMgOg", "F_IGiz2IpljcuHiDPZUb_Q", "8BV82epbcZs6JtUo7f9PlQ", "cUAb17O-KMaP1M8HjtbPtA", "MfknWfoPx2oilsyUK3kekA", "h9oGTdr9uhNWQvu0iS7oDA", "U2518Ly14sUarR6oGtevxA", "lvqOZ8n7XAl8h88T3Y9R-A", "wgmc7IyDyfMINtUCAPaqoQ", "3yBusRwPYtMCpaBkEyhyJw", "-zJKgPDHXsvRALeae1ctYQ", "SsU9BmqDebTxj8it12kNlw", "Gx9m-uVNSAua8KdVyiQfGA", "U_wcc2TXMaKhTpjUuyxiKg", "mC1L7k93BacI_XP33aeThw", "2yZghjSHZ03n8rD7pZ8fvA", "uTivCeeeBrFWewZEvGC27w", "c6QndA-I8IB2LZbnyhhrvQ", "P67OASTPpII5p0n8ZsGicQ", "LMnJLT5CVqvGo4jS7wahSA", "Jw__vRfnOSlIIwDPS_ddwA", "7xadPF7GfcMfbJV6jLGGXQ", "LRwRkjfxv8EWynwGL9NROA", "i3coGBsgXjOGYZ4pfHysaw", "WEG-2lGg0WRs2qt9tjRCZA", "nUBZcA0zunWtR-WkyCgBOA", "8HDveMXcAWYP2CuWPf7FGw", "9YZV8W7IZe5ZXZp17xnjJQ", "OmQIIWHbGorYuHq-rZSjww", "sTW0gS1reTlPhrZYCDKH7A", "MKqv8jfab89t4KK-SAECSw", "-z0TEVb3YpYbKpXZmJS0oQ", "R1YI4LGoDGMvxxEJRUl8lA", "Ma_gwnVShENgTuhHNpAvyQ", "BjtJ3VkMOxV2Lan037AFuw", "Mq8wg-due_2WQApW8GkSvQ", "DQIh6k1qAPz5hOVM4iGOnQ", "BvrB7UyjWmA-kBKptQn6NQ", "_OHaoJFgB9-Nf05Y_IeabQ", "Swzv-yUQkecpkiXBJu4mww", "qGDvXBf2BFswRBa-AfzJiA", "eOO3PRmLIuaQyhaOeJgSMQ", "DTEa4cIRdr6T4jaIw1xubg", "-r48DjK82rsDovIZT38MUw", "W4SVZz55F8_9vWoau1iWDQ", "h2rWKBzMpSrvASMgGds4uQ", "1aek7k4C4Q1yvs6QabZKww", "4AmLaW3wvhY6BSD8ZN7gYQ", "I-DTpIFtlKcw77NSgNyIRA", "zgB_HzSDhQU2PkrAyw-zug", "TBEiWGQoVXCq5sYuOzeBkw", "EBvMDMZR-95B_Ov2srhtrw", "p9TaVst1WUJNrKe3b6zKvQ", "OS2LGISkzN0ClTCQmq18GQ", "WkpWldKTNfOh_dSDRRroBw", "WO1LKULyWLzl5wpIxUQhrA", "ReOQIiMmlKHZbHHXjOcsTw", "3S0y_Z2Y591H2A072gYPjA", "1_ebb-5oHlLrwNRHMSU-nQ", "djxnI8Ux8ZYQJhiOQkrRhA", "EL7s606hrQlzu13jD6cxUA", "jrMxBHW3SlUGVGYWvPsHWA", "8jvpsHAbJLRCOWGppp0_0g", "pGttXtW6dvnh6Zc7Vr_3tQ", "argaX4ADH_Wczq2ZUPYLNw", "Dj77pkw_EZJvR-F4RIf_BQ", "MNLPwQUL2ua0XjXtD6AuEw", "EOLuDCK8sTRg4hsnN8maPA", "43NOu7ggRo4o6YyxoqKukA", "LvlPwSyinEyE9QjcM-t1FQ", "XuseBG1gQ4hT0Qbzykq08Q", "vj-71bWcddq5l-FEkThVbw", "mrO2R1Uc_DmKKEtH2VTNDg", "4MHFQcFfHzVe4ISx3lvHlw", "Ki8aCZkZ3G6uce-2duu1cw", "i5o9heILJtx3Yrwm-BdviQ", "ghGiL52X6udHMxWgvKjRig", "Wh2Y4k8MPPvBAGoRu4WCNw", "TNDp-pa7IHl8SlssQxE-5A", "EiwxlbR8fb68lMgEXhcWKA", "5-dGV2Ci9S-gSUc__GIyvQ", "twOt9KvipEAz9X1--_jDMA", "41c6fz5pf2YzTDBpUdqzAw", "Emv95IbnE4TqHuXJyi_EHQ", "vMAeu0CCKDeb6zRjAuf1MA", "t7R2npYmGrKTCsycALT4Iw", "ClvfOUUXUyXpecRa6YsDUA", "SVL1Oir45owS_oKg-ylqfw", "tyABhNSjpShd190BLKF1PA", "rD1-riyyv6GqTqjZZwqgHA", "ZKdNk5RYb9ZgYYIS01FUrw", "iIFkCL_89t9bWWAOVvhG8g", "tio5S4P1afk3zP1F5SYbdw", "oNv22da6dEEq2w2gStsGug", "3EIc7WAoiojTFdy3TGOMfQ", "GaGMN2prMUDY7Z8yGPsc9g", "hej8cSqmK5Ooi_ZGCgwrHw", "HYTk31SozAd2ieDIqPC5cg", "a699W_uzM2CUteHZqpDeLg", "t4_9-iGmx6JvONrCUdmF1A", "YG5EroFMYByZODecz3U_kQ", "qeqscJwLj21PPu48Zv0szw", "9YzE6ybg4Trnsd4kkXWEnQ", "sd4E5iKUZotDEeiF3cC81Q", "HYQoxBC1y1DGPq6pGP09Tw", "fgUJTSMFbWbm2GBqsANKRg", "65qLn7t_qDoT0lB7oe8zpg", "k_VpB5MQhiGZg2EpUMMILA", "gUAjHUCuZZzuy906CBFAGA", "axNHjLGaj_aFtx-yS0q_Dg", "Q-1mnNFpKNbSta3sF7W7wA", "zM4m1xu-6ewaga_GFB-B1g", "naGbDsV0L4ZwwmwfU1I-Qw", "c8LU5Bpc12iT3hO-n7Tigw", "V0-zmQku1uWNkHeoXLHanw", "RMRVRXD-18xUEDVt_hp1HQ", "TWobfs5CwJP5Be_GH3IxWQ", "v66ek6-aC-UvNGlVQ-eB2w", "SS-KctoEXVw16z1s4RIYmA", "YBYMLaUJNaST5TD6OUBr4g", "nkMPAu6jdq4RZy-gEc--dA", "H1VbLkqs6Uu_vFaTvLYyHQ", "08gMkDtib8IIWpDUjD40zg", "c7Kc_2h714LIwYiUC6J49w", "20Nk-sl8WFYmMwvtVnBBrg", "49su1Md2-kK1kvQwVkcHrQ", "h8pthOnqCxV94D8-JkZXCQ", "HURurSdjR3HqcVxRBJfEZQ", "CpxD4u2gMO_Gf44zSsxoLg", "j-TMFJyTMhR-3njtS-SsLA", "xnpw6YZJ96_LNrRmhKCiZQ", "LvL7XDgnMYkv9WTo7XMbUw", "Abw9Bx-bI2HFG9QRKFntkw", "v8TuvJ6b4215Qp84oSuYZQ", "Yqth7-wYhvF5q_hQaHGenQ", "BbBzub67X5sAHHTEtk2GAA", "Jw0zJgMDnKp9qrgKAcZWPQ", "WzudBEFeQnWl40asMb23yA", "c4ODXwFL0tKdP0BkdcyE7g", "s84pefAbuXnkGXLGHDLDYA", "HeEq3WocDssVr0DgkcR-jQ", "LHkV0SN4B2vEkv4-_Zyy8A", "NgX6wFfGP8i8QZZwIZhZbw", "EeqjGQlkP0jrgki01crnMg", "z0HiuDcai8S-2oPV9J9sIA", "iA_pVvHRqREXX3s57ganLQ", "RXHuqqw59JFsk1MKqiwrWQ", "BuJ5jIftTQdtW_5WlzVG2A", "MTHBsAYN26j0KimqRKTa1A", "w4zEoLWtxoelX7Do9uaStg", "CSfjaTVpxugpRNEd0RtsxQ", "vzI2SuBs80g1chJ-G73J-w", "TyleftyvzMsWbpluyuSZjQ", "gFeitEePLasRwXKaINN6_Q", "bV2T0p3sD811XnZEIOQnag", "wvDQ3XhP4lt4RnljLNNudQ", "97kNLwiDqDOO_hO-V0sptA", "LEpuE12HSZDsKhHbki2stA", "0nOIH8qIMnmZdLCTemnRsw", "WWnhqRnWWjutMqh-2SzEuQ", "unO1Py4QD_Pjo7guhRB6gQ", "_a2rbBoIF2Ur4hqZ2KtNeg", "4eR6hYFJcBHoAqhuOS07ww", "uQ6GQ6Vppl43W6ZSiTj7cg", "gmIdn5C2NhG5pqqxULFjpQ", "zR1hSWEJXRNPFuduTBBZHA", "7vZ4ttCH6S34T3x2ywdBlA", "K_8cmdRj4gpzwANwVvf6fA", "F_5_UNX-wrAFCXuAkBZRDw", "taU-uxYwYs3nywMkVm3ELQ", "QdKGcgPOOIiWVoknBEuFUQ", "Hxh8sM1kzFIz_5ofv1ZM7g", "Xb3iIj4I-tHMe6TVWN5L5g", "NAQ_mjZZaDqVsAgU4fkh6Q", "_aSs5dSAabuwnXUGBPzASw", "u_tsaDmAgGnmOUGdbA2tNg", "eI374ocr96npSpwZmQrNyw", "9CxTjD-qO7QMGCBc-4HC4A", "NaE6ma3bmm-gkQL2pf8pVw", "9Nr3-K19_TL5vmPOaqO7RA", "IUilHGdHxziHYpiNkmQ6sA", "Fv8pA4FdvJSoXoUAwHKkLQ", "drL4C3q-v9eRKyYU54ABiQ", "gnoIkKGFEtaAAbFIBxc5TQ", "8Aq_UdlsrjhBwGWb_U-xRA", "beTVdIu7UGlPE2De4_zs6A", "Dc43j8jCChaPZq8o3L5jQw", "dWUpHH4b4cScT2ymMaoEGg", "yGHP5LUQe73kOvYQZF6Dqg", "mgAQk8xaf0uzqSjdz7IBXQ", "_Oh_YYX6_HVhSRnCdeQGAw", "Rs5OAD8I3Fp4G-j5IN05SQ", "6zr43bKAuC_NUYOoqlJCBw", "wQXRDOf7Wnu6K1cKO_bjzg", "78raDX8_mwfSilx2QIjcAA", "nmqX1cxPOYHwql5e4U9LuA", "B5gJUGCkRffd4zDfc5IWZg", "ShN97yxHps7ex_XHuc93iw", "v6Pbcy6I5kDb-uk2Ychvgw", "iuKdlVt549hc2Kd9_tYepg", "d3-ScnCgjkks04FjfPwTJw", "205YvQhP0Jdgdwq6sGsrWA", "iMeBJHaZXd5M2pt37dHmTw", "qUGMYSGV24KD8QFCdGGIlQ", "XnClYmLG2mBcha2JaeMB4w", "1Px8_etTU-O0NTBLemwDJA", "t_7ngdXz_NgOxbPC0e0xoA", "ilU2YC2DbzoxMUNjEZSpMA", "zsF1HD0f8mG6WmD2T6YGnQ", "rEyssFWviRUZRw_-I64NGQ", "NR6Y46Ni2JjQcj4vDbqKUA", "LX0yWiLXHBOfvCmUogmK-g", "94GWGN4tBj3UQnegEDQIXQ", "hx0YV9Jijd54jGUnYQdlfA", "P5jw8VdVSFb1oWY9UyqcWA", "5G7SuKXxeVPXC1_AiqM8vQ", "NY-BrGS1UUhBHnL2HlD-nw", "tK20A6WYj9CeqUI-dJbEIg", "JEpGg5Abvq02QskO_dQDug", "Tq6D_IwLwj_AfuCS4igq_w", "sl-LXAhDMIfRLPYLTcBRaQ", "74-QP_tkLrttRM9pUNrLiA", "4w1MaiQc_wVcCymCC9O7rw", "PuTLsJ1S_rg3zQGXRjvAMw", "oyarlhGULfEvBujSbkHyUw", "D2j2lT03Wb7Y1tUvWc_q_A", "0B5zsxsq3CutuLVdcR4TJw", "KUmin6YNvQZVdrhVED7GAQ", "McDOL2jwi-llUunfk_dlFA", "rL4UqI9oJqqdr8uwlhv3dw", "86q1YWhJT7HFBRoCSXI72g", "zZha2AcC31exjvxun055PA", "S72WLoB1SUdLm0SBmp2law", "8onBcSo9aSC6hUYeZJSAUA", "T16FVXn61_y_-wJanVq6Dg", "nK_aZKxrVIIgehcMgGcRRA", "3X1jq9bEOppZi91ti21_Xw"],
  "fans": 27,
  "compliment_note": 16,
  "compliment_plain": 52,
  "compliment_writer": 14,
  "compliment_cute": 7,
  "average_stars": 3.6,
  "user_id": "aw973Pm1nrTbRjP4zY9B9g",
  "compliment_more": 4,
  "elite": [2014, 2016, 2013, 2015, 2010, 2012, 2011],
  "compliment_hot": 20,
  "cool": 67,
  "name": "Kenny",
  "compliment_profile": 2,
  "compliment_cool": 47
}, {
  "yelping_since": "2012-07-21",
  "useful": 0,
  "compliment_photos": 0,
  "compliment_list": 0,
  "compliment_funny": 0,
  "funny": 0,
  "review_count": 2,
  "friends": [],
  "fans": 0,
  "compliment_note": 0,
  "compliment_plain": 0,
  "compliment_writer": 0,
  "compliment_cute": 0,
  "average_stars": 5.0,
  "user_id": "_nJ2WdJRAL4toJ24dag_Kw",
  "compliment_more": 0,
  "elite": [],
  "compliment_hot": 0,
  "cool": 0,
  "name": "Susan",
  "compliment_profile": 0,
  "compliment_cool": 0
}, {
  "yelping_since": "2008-01-14",
  "useful": 0,
  "compliment_photos": 0,
  "compliment_list": 0,
  "compliment_funny": 0,
  "funny": 0,
  "review_count": 83,
  "friends": [],
  "fans": 0,
  "compliment_note": 0,
  "compliment_plain": 0,
  "compliment_writer": 0,
  "compliment_cute": 0,
  "average_stars": 3.78,
  "user_id": "B46q0uJGiuzTtcYXknkgcQ",
  "compliment_more": 0,
  "elite": [],
  "compliment_hot": 0,
  "cool": 0,
  "name": "izagui",
  "compliment_profile": 0,
  "compliment_cool": 0
}, {
  "yelping_since": "2014-05-16",
  "useful": 1,
  "compliment_photos": 0,
  "compliment_list": 0,
  "compliment_funny": 0,
  "funny": 0,
  "review_count": 5,
  "friends": [],
  "fans": 0,
  "compliment_note": 0,
  "compliment_plain": 0,
  "compliment_writer": 0,
  "compliment_cute": 0,
  "average_stars": 4.8,
  "user_id": "3GKe3Nscq7Jtrt4xUbf_XA",
  "compliment_more": 0,
  "elite": [],
  "compliment_hot": 0,
  "cool": 0,
  "name": "Monica",
  "compliment_profile": 0,
  "compliment_cool": 0
}, {
  "yelping_since": "2014-05-14",
  "useful": 0,
  "compliment_photos": 0,
  "compliment_list": 0,
  "compliment_funny": 0,
  "funny": 0,
  "review_count": 1,
  "friends": [],
  "fans": 0,
  "compliment_note": 0,
  "compliment_plain": 0,
  "compliment_writer": 0,
  "compliment_cute": 0,
  "average_stars": 5.0,
  "user_id": "vA4LM76VgKuw7IzEBdyecg",
  "compliment_more": 0,
  "elite": [],
  "compliment_hot": 0,
  "cool": 0,
  "name": "Kirk",
  "compliment_profile": 0,
  "compliment_cool": 0
}, {
  "yelping_since": "2011-02-06",
  "useful": 0,
  "compliment_photos": 0,
  "compliment_list": 0,
  "compliment_funny": 0,
  "funny": 0,
  "review_count": 54,
  "friends": [],
  "fans": 0,
  "compliment_note": 0,
  "compliment_plain": 0,
  "compliment_writer": 0,
  "compliment_cute": 0,
  "average_stars": 3.56,
  "user_id": "oMT1lSrACglwgFPDBYEIuA",
  "compliment_more": 0,
  "elite": [],
  "compliment_hot": 0,
  "cool": 0,
  "name": "mmaaxxm\u00fcl",
  "compliment_profile": 0,
  "compliment_cool": 0
}, {
  "yelping_since": "2017-12-05",
  "useful": 0,
  "compliment_photos": 0,
  "compliment_list": 0,
  "compliment_funny": 0,
  "funny": 0,
  "review_count": 1,
  "friends": [],
  "fans": 0,
  "compliment_note": 0,
  "compliment_plain": 0,
  "compliment_writer": 0,
  "compliment_cute": 0,
  "average_stars": 4.0,
  "user_id": "OaKaMTSVSqU0TZY9Rpbd-w",
  "compliment_more": 0,
  "elite": [],
  "compliment_hot": 0,
  "cool": 0,
  "name": "Louey",
  "compliment_profile": 0,
  "compliment_cool": 0
}, {
  "yelping_since": "2017-11-09",
  "useful": 0,
  "compliment_photos": 0,
  "compliment_list": 0,
  "compliment_funny": 0,
  "funny": 0,
  "review_count": 1,
  "friends": [],
  "fans": 0,
  "compliment_note": 0,
  "compliment_plain": 0,
  "compliment_writer": 0,
  "compliment_cute": 0,
  "average_stars": 5.0,
  "user_id": "N0Erq1dB7iXtkBdKrtArdQ",
  "compliment_more": 0,
  "elite": [],
  "compliment_hot": 0,
  "cool": 0,
  "name": "Tristin",
  "compliment_profile": 0,
  "compliment_cool": 0
}, {
  "yelping_since": "2012-12-25",
  "useful": 0,
  "compliment_photos": 0,
  "compliment_list": 0,
  "compliment_funny": 0,
  "funny": 0,
  "review_count": 1,
  "friends": [],
  "fans": 0,
  "compliment_note": 0,
  "compliment_plain": 0,
  "compliment_writer": 0,
  "compliment_cute": 0,
  "average_stars": 5.0,
  "user_id": "RetgmtjEJrWQeTjLYo46MQ",
  "compliment_more": 0,
  "elite": [],
  "compliment_hot": 0,
  "cool": 0,
  "name": "Maleah",
  "compliment_profile": 0,
  "compliment_cool": 0
}, {
  "yelping_since": "2017-11-02",
  "useful": 0,
  "compliment_photos": 0,
  "compliment_list": 0,
  "compliment_funny": 0,
  "funny": 0,
  "review_count": 1,
  "friends": [],
  "fans": 0,
  "compliment_note": 0,
  "compliment_plain": 0,
  "compliment_writer": 0,
  "compliment_cute": 0,
  "average_stars": 1.0,
  "user_id": "nBDJyPdJ-wn41skUV2QrhQ",
  "compliment_more": 0,
  "elite": [],
  "compliment_hot": 0,
  "cool": 0,
  "name": "Tyler",
  "compliment_profile": 0,
  "compliment_cool": 0
}, {
  "yelping_since": "2014-02-05",
  "useful": 1,
  "compliment_photos": 0,
  "compliment_list": 0,
  "compliment_funny": 0,
  "funny": 0,
  "review_count": 7,
  "friends": [],
  "fans": 0,
  "compliment_note": 0,
  "compliment_plain": 0,
  "compliment_writer": 0,
  "compliment_cute": 0,
  "average_stars": 3.71,
  "user_id": "W5GkZO-8n7qrr-Ws5nEL-w",
  "compliment_more": 0,
  "elite": [],
  "compliment_hot": 0,
  "cool": 0,
  "name": "Krystal",
  "compliment_profile": 0,
  "compliment_cool": 0
}, {
  "yelping_since": "2010-05-27",
  "useful": 0,
  "compliment_photos": 0,
  "compliment_list": 0,
  "compliment_funny": 0,
  "funny": 0,
  "review_count": 31,
  "friends": [],
  "fans": 0,
  "compliment_note": 0,
  "compliment_plain": 0,
  "compliment_writer": 0,
  "compliment_cute": 0,
  "average_stars": 3.97,
  "user_id": "58guXrSqpOxnKoeuTxLdag",
  "compliment_more": 0,
  "elite": [],
  "compliment_hot": 0,
  "cool": 0,
  "name": "nam",
  "compliment_profile": 0,
  "compliment_cool": 0
}, {
  "yelping_since": "2015-02-01",
  "useful": 0,
  "compliment_photos": 0,
  "compliment_list": 0,
  "compliment_funny": 0,
  "funny": 0,
  "review_count": 6,
  "friends": [],
  "fans": 0,
  "compliment_note": 0,
  "compliment_plain": 0,
  "compliment_writer": 0,
  "compliment_cute": 0,
  "average_stars": 4.17,
  "user_id": "Uai3Mn-Ro7LwIKJrEdONuw",
  "compliment_more": 0,
  "elite": [],
  "compliment_hot": 0,
  "cool": 0,
  "name": "Jessica",
  "compliment_profile": 0,
  "compliment_cool": 0
}, {
  "yelping_since": "2014-06-22",
  "useful": 0,
  "compliment_photos": 2,
  "compliment_list": 0,
  "compliment_funny": 0,
  "funny": 0,
  "review_count": 7,
  "friends": [],
  "fans": 0,
  "compliment_note": 0,
  "compliment_plain": 0,
  "compliment_writer": 0,
  "compliment_cute": 0,
  "average_stars": 4.43,
  "user_id": "t27CQ2vYWbrQTsgJrnNYFw",
  "compliment_more": 0,
  "elite": [],
  "compliment_hot": 0,
  "cool": 0,
  "name": "Felipe",
  "compliment_profile": 0,
  "compliment_cool": 0
}, {
  "yelping_since": "2016-03-19",
  "useful": 0,
  "compliment_photos": 0,
  "compliment_list": 0,
  "compliment_funny": 0,
  "funny": 0,
  "review_count": 8,
  "friends": [],
  "fans": 0,
  "compliment_note": 0,
  "compliment_plain": 0,
  "compliment_writer": 0,
  "compliment_cute": 0,
  "average_stars": 3.88,
  "user_id": "uoNm7vaHUs8PrxGYO5NCGA",
  "compliment_more": 0,
  "elite": [],
  "compliment_hot": 0,
  "cool": 0,
  "name": "Mark",
  "compliment_profile": 0,
  "compliment_cool": 0
}, {
  "yelping_since": "2014-05-08",
  "useful": 0,
  "compliment_photos": 0,
  "compliment_list": 0,
  "compliment_funny": 0,
  "funny": 0,
  "review_count": 4,
  "friends": [],
  "fans": 0,
  "compliment_note": 0,
  "compliment_plain": 1,
  "compliment_writer": 0,
  "compliment_cute": 0,
  "average_stars": 4.0,
  "user_id": "XyGCnY05-v_lNCxoiT1y5g",
  "compliment_more": 0,
  "elite": [],
  "compliment_hot": 0,
  "cool": 0,
  "name": "Jeff",
  "compliment_profile": 0,
  "compliment_cool": 0
}, {
  "yelping_since": "2013-06-03",
  "useful": 70,
  "compliment_photos": 0,
  "compliment_list": 0,
  "compliment_funny": 0,
  "funny": 4,
  "review_count": 31,
  "friends": ["PZbPhdy0_08tHprIJiZ4uw", "i4dhajw93ZDmIa89n6-w9w", "KyGnYa6biPYN0Ez8r_dcDg", "2JwnPWhd5MloTtA7pKUnPA", "JHwfzhZE66yCnXFEX-8-pQ", "PuTvg0qtUoPbsxLb6Kycgw", "UqFGZB8aR4pDM2vwj-NVFQ", "U_4JS979X_B-N6Q8rMoQSg", "uYnkiXOKzXnfJ0qHMc5q1A", "GOByC6q6RCCKsLeRfb9tXg", "Sgz4l-2H4zVLuAp3W-izTw", "_i6WumhVRRzKRCxDw9EX1g", "eXJwUDuUhN_lmlt6h3OR0Q", "AfmKiZxURG7SQ9nSDSALqQ", "Q-dy5IuiAdKqLrtVhuB0ww", "xfIuJuU4QdeLavhLDRcebA", "NbjZKsMFKA5zQtaAKyIZmA", "1K--_FT-3YSTmsey4BZ34A", "OAvCdAiq3twMgv95UhcrcA", "2fMInCIsKFBt71gsCxtAZQ", "OEsReZhvTuBajv-Mu06zRg", "ZAiUoWVLxxde8M4QBUMTCQ", "LOysemXyi_rfgvye7n_pWw", "BLqPXTcW5z3sWFv5C6m67A", "BizoZyaGWq-GEXCDaIdNSA", "nv9VMDvZECiyQGthQLkUrA", "ESlvCrOr8e5ziS5NHIF0Rg", "00fpwRLi_gfJeaBObrOcBA", "PDgwNEsnvNo2yFVq2LCWUQ", "i09BV4nNXBK15Hwuiqm32A", "YkzF97d2LV43vpkhRyUeGA", "wL_Ff4OYglKOg58WaRtBuw", "QeipsG5GLJqs7RWV_cmO0A", "FDgwBC43zd4eWNlfSdhZNA", "WixAShl-NKWRfun0WQkx6w", "Zl_JZhkKK29OljP5Hl_JFA", "cXXTctsJKz7PzaVL-CVk1g", "KJsqAM-XcyHjdIztq_Vnkg", "TgeJt_4reN9BMw5JGmaTSQ", "FjokSaULfBU9zrt9q0qSmA", "uVICa56UifkomduUflUjsw", "fe299uDIUqgsY_BIzp0fmg", "AEZj2axEeiAMrdKQke9YIw", "F-ypbf06PA63pod_L4mTcg", "IfkBY9HaLtgclXEIjTKnQQ", "RvCfBKXaWF_ITt58NOyUJw", "J44wj6tDQkJjhb4iDfjzWA", "Xq_lVUBJEwQUo1AEtmqa8g", "o9GsbVJ-pyDEKp_vvstyMQ", "nYhvP8uMIsJ2zjT0HJDuIA", "rrDA-mfsLNSOJ51Bwx5PHw", "e2_WhIJ4g7XMcrXqhACP3w", "CY3shVoIVpi4F4O0NgCvkg", "ADZsvEfLpxqggCIndoLGKw", "oUxLcMj0FkXbhCSfot6TAw", "7xI3zVZcrAYB04yv1NKG9A", "RA6xTR_f0CtL8icJwz1PTA", "n8M_Bwx-BpwPSksXPmatVg", "7PcM-zmnzLYHBSx6FyrvCQ", "9kYXZCZEp15JyznelNTskQ", "zb2AjGVXdEiFai7gixdy4g", "-9jp46rHS9Ka-7cUyoZDDQ", "iRtdXl_foj0PX8qV3AIjlg", "sDmLuolKwjDGK6AJxoJ89w", "0a1mfs6BQoQpcMJDGmvUgA", "Crt38SgWtPzabd6HU98Vng", "ghgBlvtC7Sc-5i3jxxgm2w", "vOKGtDoWR9LPIxqIIo4dWQ", "2Q9eCtuUcgJgu10EpdyioQ", "9GhkIuRKeqolItwJyxcnhA", "z76YX19tpejAjcI2j8VQJg", "rpUAKQtJ32EklkGMdoGNLQ", "g3G-F9VcAo75OG-1ucjOBQ", "jVC-_nPvZ0ctQh7dJcf96w", "t3qHyrKhwIivdCUIZWt-LQ", "5047GwBvEORXNcNqs5SA8w", "XqdrqGbXkNzz_OAg1eUl-A", "SBC7vrkvqjSO2sjKsVNs6Q", "iq8Rt7BUYDRU780jkKSTpw", "rWQxCdH63KHVGr19fH2sVg", "K0_6nMha94eF-vAeU8A4bw", "bG8qhXgATFJ117dSQRKvWQ", "P6MfwQ6W8zjzdyOb87CHgQ", "eV9QEAuYDy0xenYsh6WTnw", "Hll1Y-mZeITU_ILFO6uedg", "tGpPuToNjT7yuJSjGgmOLA", "FgaY3JpYHLdIBN4OeFWN4A", "5lZ6-SZZ1R7a0fHi3YFFzA", "2mD0ycTyKjQYqJc8jz4kOg", "8RuwJhYJGD8jDwRiL2jmTQ", "azpJa32HxzptHema1KhcIA", "c4lK4kxAHsFRQtLtab1f2g", "TnI5eNcHaUExCmPf5weLGA", "z2mooewDWT6ZP-77Qn5qaw", "4bQc3HS80-RyH_i02xhuqw", "R6IH8XO65UGkx2U4bOIOTA", "ibcESjJotv9x6vqypzbPXw", "c-Rk0Z_vTuixvY4-HEPy_w", "SoXhIfcc3HWdi8mWT2Z8pg", "ddtz-banb-uoacvtOUYu5w", "pOyXMjLIjriZt12McLJ9JA", "psItdqJEfWQD8Yp-CobhPA", "mD2ZsT2uUibnF47Qu1-t-w", "ha8WePK2vS2TD_w74p4LWQ", "us-JHgeag46CjmxAOmtcyg", "SGFwaDf-AhttBUZBf7sZDw", "0aUBU1Mgnv_ZWbqfk-LkQQ", "49KID6LHue6D6JLwFdjjMQ", "RQt9iirWDyCjrTXUNVwV-Q", "zeRIM730qENV5L_GUHWfYA", "irbKRZyCN_RPzeBepCN7XQ", "l4prewmNPMpVaEQIIzXBpw", "Gx9BmTAKvZYjaeEhbFQzwg", "rG1hECOdhMEFwjS9t4Q6PA", "79NQMxNpdfA9J4WddMdpEw", "MCoHgGfjpstHcwTnLNYTtw", "kMFFTk-WlIkcIr2m0ETGcA", "-nj6VrkFgCzaMAcRFV-aMw", "WljZ-8ioKobeOGRk1Oe8Hw", "1vce_B2mPqTC5Abxqjjm6Q", "NS8Efqlpz0hxe6KYqdqTSQ", "URRXydBBv7ekiUFpVkhHzQ", "EqU7zAwQqXvC2QMT-7dI_A", "2xUuUsO-5mLPPkTAsZqy5Q", "IMCNknEJ0nl5z_Q0HWmVTw", "uDqqvYcI5snpD2yIdmvttA", "ukC8eCUOY4aSKk_yMpG98g", "OC8SP_aM6911KR4M1pN2sA", "YajrP10Lv7Dwnsf0RZOtNg", "2OhX25gsQRVcG6ZhHpiKYw", "lMfgfDbbdUrxjs3UQfSFDQ", "kiagI91EfcjOBTmTLDOApw", "Bt5vGVCUUmrWmVFAcAd95w", "5fLE57ylKoDPkqPoMALILQ", "2M_Jhg12u6yoS2gsMjTbuQ", "n3kLgL5rvTNo3tqRzExdXQ", "eEVYppG50sdvhmUlmKoMWg", "Nma_WiCwU6RJU5A6isPYNA", "FfacViJFRLD20rkqXvG0qw", "z-GG6dIj0TdF0lCTZb4plQ", "xkForr90S6qegQomZjdORw", "wUzpV15US_FUA1pkLAhJyg", "moX7x3UrWIXn-7NlIXAMgA", "LHjygtCUVVmYZ7_h6KK9fQ", "pHluhGuVxAr56T3laMyl0w", "ecUUnVnBJCJs7BoWuwyCBQ", "QJhoUwDsOyXzXVt_oYM32Q", "8b0JlxXkr0UASKfQJ_-GRQ", "nFFoqgJpA4FzVMdqz_0p4Q", "FThBm78G9akz65o0jWU_Bw", "FC-FGyuAB8_2jyI61N2Olg", "ox72PvEQGYanneirwI5kVg", "qSpTiWuxVo8RSOYdMzbnYQ", "6JOgS83_cjS0ir1OzdigKg", "w7JkuzaHlgkzotgAUgeBkg", "HwZm1BWLqJkVXLLP7OPXRA", "Flgp0hLOzO_eXlQfz6s1lg", "x02wDkPplH3Pri8aErttYg", "qlN05k3W9UKLlNIqqs8K5w", "Ofcx5j94ih2kefnVzuaMAg", "GSVbyrxJfrmcQXBWFtpffQ", "DVCz3OPuk4Yju8MVnBTXgQ", "yG0MCDw8UJk5A6WomwqR0Q", "7cM2CMedmIJyGMQIeMc9Mw", "pp-1xE4-lfGqunpA19P4Gw", "t5IWRyc6NdT8P9PqueNeug", "3s6fFj24-xUsLy3EO52bPQ", "JM3LgnkSSBy-rqEqf0f9OA", "ZpolS6CX1SMv5LwWlRxdVA", "ZguDJRTIEay9y9GJrZBJzA", "bTneh5RmBS8Se9KFHNwTtA", "GM58HSGUFnzylr0wUWZu7g", "xR0X7lZc_WC8RZlP6wYVkQ", "qSbWPrFOglGQRu8YDQ60Ww", "MXc-wK8q0pkK1nwx4RHFDg", "2QHnGZUriAFP5j3Ps_2vng", "OeN-eNyC6oRg9bj1JDv8ow", "vusLIDYJeE1K6a4IEYHvrw", "fY1ZbNb0OEhaCJS8nayr3A", "krnDlLc3h2GwTx11X4Vrag", "loCshn-4kH5u0bPF1-MMQg", "uHNeURNwWZRKJFwZZq-A_Q", "6gBnkBvLz4D0L3PwR1tGLw", "s_Rddym84XyXruxbbgsIog", "gQZsSsuAyyqIo3KpsuAy_w", "kf1YvFLBZcb2OUIsZzwpyQ", "KEMENzqPmgsVCfdeeaO2dg", "-b0yLcxXY7uFzFqkYiA-iw", "KQal3eFjR75stE6QSAOJ9w", "9BIDjDsVTbSLLpYdOneOwg", "6Ng2TYmCkp0snxvRhw5BfA", "gJtMK8EC1cNR2kr-3OM5Iw", "Lcb9ZEv5OuNHe9KKxPtrRA", "yMIGOLGdIhjmNvrGAQDC9A", "U-y6W7IpUaToQA4iwN0Fww", "l6xVpup9ocNKLbK61dViPA", "nBXubIdbK-EF4afGNQcBnA", "RVGbOln3aBok1jqKVVjfHQ", "ch58x23P37NfZTiOEdPG8Q"],
  "fans": 0,
  "compliment_note": 0,
  "compliment_plain": 0,
  "compliment_writer": 0,
  "compliment_cute": 0,
  "average_stars": 3.76,
  "user_id": "pzpbr9mlagHhDRdin8DvPQ",
  "compliment_more": 0,
  "elite": [],
  "compliment_hot": 0,
  "cool": 68,
  "name": "Tisha",
  "compliment_profile": 0,
  "compliment_cool": 0
}, {
  "yelping_since": "2013-02-13",
  "useful": 0,
  "compliment_photos": 0,
  "compliment_list": 0,
  "compliment_funny": 0,
  "funny": 0,
  "review_count": 2,
  "friends": ["MkXARyNby-scUaINNA6aCg", "ITD5f15-4cySvVyXvBwKWQ", "hHEFFawG5OBQ9ba6k2ffYA", "5yQ7PgTGczwKVeDTnQ_WYw", "sMREXZ0RmiS0NerfkCu55g", "Rg3Su2kw4xUTQa2AvwuOcw", "j6U2wUeYLsltWw2Fv325ig", "ON9Ib_6EBOnihgn5iRMQAA", "EKIFI58ZybcuGJa1lRfaFw", "IJC6b9uddMYNuX9LeC2WJg", "mr9LBMQcorszYRKjTY0f7Q", "M3hYc7XvyD6WmHHaJNoT7w", "HEm8BeuKzBbP3XWNewkseQ", "FRlvwA_FAAw7Z40lO1fxCg", "8--2c7UXtuxnZW8uw7_k-A", "9hBFz-n2iA41ZBAU5HznSw", "pgYdixy1utPGSlFvXEZ3hg", "nwu-fUVkmFEm_9EbRLIU4Q", "38tlDbO4dv_4Uf6_AaBQJg", "_GXMqdV3E8i0uNZUMaFA7Q", "cNq3Sbb0ZafwNB7ZKyA7qg", "N_iZDMnaRSY0CMdPStmkOw", "BTXHYobVnOdA7N13wrngqw", "Jvlf2oddoNfdYJaOXkKjKA", "RNXsTwQu0dJwxI1cJXCIyQ", "BB7jZQEg6na-qEFTTuKUnA", "IsPd4t6e7rYDjTEEdOoCfQ", "dPFaRxZ7dVDEEyNi1vSYLA", "QzLxCY7mfFyjDc5tww1Xqw", "dFA9qIVrjJWcJrMnDfWvlA", "dd_7ueedu_j6zl6CMabXEg", "vPE2akVwM-i-6_x9bcNG1A", "Z1-ZI68w9MCujQ9EE-mIjw", "6HU7-MrH23PvVYVmeSrJDA", "eGtY0lG1Ac13Vd7Z-dn2kQ", "6a1r8mWZgfG12m7fBU1LOg", "62w61f9OwqKa8dHN5RgrKg", "eIIyihGpqGjMcw5dBwAKAg", "Q8vasuaS8UuFIRjsNgik_g", "bJs-0-GndJoKPCBdkqn9rg", "BIlopEPJCOjEUsLSuAMcCA", "apNlbDhi9DhcftOKAUC35Q", "L8FKHOxZ5x9TZhHc54UCbA", "9JA1t9_ihfxVN6d46a4Q1Q", "UaE0u0KxMXBiiG73Gt5GLg", "L_LgpKChPiyJyXfUVsQAow", "tSQhpZ1UvXE9u13tvxlfIw", "MF9Nfn_tEEaCA38G0qjimg", "L8_IuOpLsan7yLOTygyEyQ", "QRX1pp8Rsd-KMEQ1qvIC6A", "8l_rFK6qB6V_jtIFVjjdCw", "nBBEMOq0QjK3nVEQKaHaxA", "sl09voKuhJ2duj4THxrh_Q", "ih1H9tBHp1AewzwThEsUlg", "gnrLLlLQkvqfEV5P9-uwaQ", "6QHLaOtNyw5x5yry9GXSQQ", "BG-Y8YRof2kiZDYiwp0HCw", "ly5zwzcM4HJx6EbptIbbTw", "z_7ogC_80sS4H6PaMkRCiw", "nAe6JH578RZnSkcp40s0XA", "wB3tIxDDLfL0uSA_4iJqAw", "aS0RTO6duy0XnAJcW1Pg1w", "7MaOoRe-T_rcbdUfIs21eQ", "6nLWChFN_WIBZ6vrojN86Q", "2Z_hokKyxZc7C-UtKau-Ww", "qBK_3Y6JfPS9KdWEFd8p4Q", "MrGaG4Zc9JfA5zfihNrWbg", "YZl97tsCiYaK1mB4xQ7EKQ", "dV0hKfs7hluxrIxMehylkg", "JZxrZHfY6RpHuST6BSkwgA", "PXsCZ8DahFVvWgsZEfuixw", "cOltfuEVB5ABvAqAGh4QYA", "LqPYxMPWBHvbGxBdx8M7Zg", "qs-RiiP-FOUHh-bXCzcdcg", "dNfrsdeVdfjZ6sF4V4DOAQ", "9s4eoDWQQHua6pBxKcAFog", "mkg6PsNx_vjnEdNjSQjfaQ", "ZY1XpXOlf4StEqzLitnFNw", "EeMOQkDKOitnCNJMaM55dA", "E2mDmoGFX3DiD3_APtKqXQ", "GcEsARZ1gevXIK9dheQuww", "hdLm6zfSWndSwq0ZKqon0g", "nnlNP10aB1QrJt037gf48g", "MvTNvJAUWOVBxM6KwtMhhA", "yf-xFY3jreV3GdN5h6kZjQ", "XnOSx2mtkXjuLzk1RGdTWQ", "jyllfjOhCOLb3thJJUfyKg", "CLvasnsieEcvYrL_5AxGaw", "SV-x9jLClUp5tMlNYBBWPw", "v8rytRVh69CG5PSmx2X5Zw", "FooLq0zQRS3YF0P-mMYaPw", "zf5gtqtkMc76CJi163nPqg", "9Hv4_if0g4B2pycRYWUzeg", "gQET9j78tYenpc9xnJXyqg", "tPNc7x9f586OR2P8ym-vUw", "luUgZeVEfxXTePCV1qQXIg", "fYhqTKtjE0aFMUKZz9P6uw", "XRji0PfCl8jDQMCDH7CRYg", "-SAzSB4Gm8xf2izyPusj_Q", "2T39G7td_tFbo4pJ6y_1PQ", "fZEKjgVC2TkaHDZeh3RSoA", "2Yz3zdS4knKvnFSXzSDYMQ", "Z3XszLAwHajXeiIKtEckig", "q5eDkLNF0Spi5sEFOtATqQ", "Wqk0-0pr26Rnz1jdOZoG2w", "oDsy51TnVhfDodWWPgwQgw", "TSSVpYxc4GnMlkLgsM2Egw", "mqMLoU3ugcqFuxCQRuPoHQ", "cUjFyycyXgIbc4TYYlNeLw", "wN2anOfhinVZ18NLh1rLog", "BBIjtqHcIcJ6gUPrbzjJJA", "mZqNRmSvkRLpRNOAiY0-nw", "-OBCZTkgJRhi1ghT5R1DYw", "d0NLFbv9Tb_Y0vgVuPDJZw", "I0ut7EDPJjul_62mbP4QkA", "WXCioXQi2ae-Gwl0alU1Rg", "Vpk9WDsYNqOEJMwj2Q52vA", "v557OFPxHnNFEaxHfXC9Tw", "3mDX-Xav7TvbXzxED_-BuQ", "PLZwiR9mK-em4slRH_48JA", "ehb2h4Srwm3IrfimH2_9Kg", "WPcHiq2lTFiPk2OeY1V9Tg", "kihtAO9i74IU_QjIVGeG5w", "iIb0AxFjaP8lS9jXcYvajA", "YRjjBFGFIuWdUcKKcq0Eag", "b5WndL4qXzi7sz6wpQMkwA", "gdo960MqxQUY7V8cxPUPlg", "0JcOe3g0c7yKq3Zzmg_4UQ", "iJWt356B7wimmixYYHURtA", "39y1wGst1QrQOjokVss8ag", "EveQrg56YxxyLfsu7NCIYA", "ivwUOTffXJcTv4cv6V0bag", "k3I-9cvAJSltVdDMN0lkhQ", "xSBkxqUkDIfcY__te2dBAA", "DkO-4y9vRMmlkcsW-0iwGw", "tdG41YwEtYjJQZJStBCjEQ", "vS-1TqtR2tzWuCvAcddmKw", "8tRqtz7di1LSSOjvwhJddg", "DHlKLHfGPCm0mRnrTtPvMg", "nompNeAVxUaaWaZQevqJaw", "R-a1CM1qiEQCgPfyc6d_8g", "salUoDvsJ2xLIlGiRsnc0Q", "YjvGKGDAMTpucibawZqj0Q", "SGu5Jws1X0_892nszTs1Aw", "I983bd6oVCW3MFQmuiANHg", "1jVdbsJ42cbs1fw_x0_-2Q", "ZZVONTdDp4CQIBMliiW5EQ", "B4_qUjMiZA0HnFXsZ0Qffw", "_4dmiRF5xROYE-IPL2iMig", "hTLyXCDkvSCGQFlS2AjhOg", "sFPqwrCAMY8ODZ9CHpAOtw", "QfD8rt0p7kg5DXaW5tSQGQ", "CV0bsb01_BGljilE0Jx_NQ", "QhaFopoeWt8ITyeqG2Ao_g", "_EcZFd_huyqxte2hx8JTbA", "np5eTSruUTPdOdKYRPQ1mA", "sUGX-i9J6JgHwQXOpAtWIA", "0Vj65r05dVKHFqEsUK1kKg", "-j1cHgA8NpujCeqYji4tWg", "C6IvzQc9BUnGt8Rsyo22xQ", "sh33tefYIPg1NSGGEjNf0g", "0gNL987pannlvWaMJoznzA", "g6Lr1cW34IMU8PbIqVJDeg", "wuVusxrPEq1y7e7fTF0xoQ", "t2D8qj7wn-sa2MiVGhpYxA", "trrgYEe3zs88AsNp6mlFkQ", "V20NDIIdtQlRpR77cxeHfA", "t6TzNUUY2ez6s-GYOLs4VA", "SLVKZ8qwGPP5agJCXGv0tg", "HFpth3GKEgyjL5QJG2Zqeg", "0AdIOAxrjC-58WcCVOHonw", "R1qzUDQpDii2qu60imqWTQ", "GZ3F6UHoQb0kqmUTY_dU5Q", "La9r_Z9rGf29pWChpP8nkQ", "Xs2qfusSOXRQ-oZNP_-cJw", "LakxxjT2YSAK0MlxmD1aaw", "MDGW1wOYizDhiPZe5Jl4Ig", "q4vL-tFKodxCfwLtVQ0tjg", "Nh94Uz492TAA3qsSgc0XUg", "E3CnM51WeXImFFOzyfYTCw", "NSOyYOEq8jGB4gsSDyo2lw", "PFjoKueCnPStIsoBAIO9Nw", "qYDDZHBqcJ29BhXRzwTpMg", "ZsSWZYeONDQwomiBjORfdg", "R00OJ_6r5g2jUYGZOnRl3w", "KHGGwwULMbOD1bDB81O0hQ", "gi_q80_H3GozCFuXTGmVRg", "ELVbL2Jk1SkC-dKMtWV56A", "UV2CY3Q-DvSZ4hEQAVR3ag", "7K_COmgQB8CO7fd2CRDTog", "ZDGlunQF3_Wmpip6z1QBKQ", "JcIdHm1hGdFkVTLjjZfg5g", "UqJx_GKaxWlikxR8nfkq9w", "e6D9PjLw5ADPazP-uCrC0Q", "FuMmtNvVAL5zzvJHjfY_xg", "QKGt9fXB7582NpjlS6XdbQ", "i-Rqe5CPZ_t_6MmRjmombQ", "NFHT1LSQ-dCEh-mESqcXnA", "dKc0oFOuVYIqPJMib6tR6w", "G760cg9VaoWORcbxPusR8Q", "KAioyE7ik7E6ORMsFfm01A"],
  "fans": 1,
  "compliment_note": 0,
  "compliment_plain": 0,
  "compliment_writer": 0,
  "compliment_cute": 0,
  "average_stars": 5.0,
  "user_id": "B-ruI5C0gr2EJUt44cWX0A",
  "compliment_more": 0,
  "elite": [],
  "compliment_hot": 0,
  "cool": 0,
  "name": "John",
  "compliment_profile": 0,
  "compliment_cool": 0
}, {
  "yelping_since": "2010-12-31",
  "useful": 0,
  "compliment_photos": 0,
  "compliment_list": 0,
  "compliment_funny": 0,
  "funny": 0,
  "review_count": 6,
  "friends": [],
  "fans": 0,
  "compliment_note": 0,
  "compliment_plain": 0,
  "compliment_writer": 0,
  "compliment_cute": 0,
  "average_stars": 2.33,
  "user_id": "MQkIMPVmgCoC26Nn5LdkHw",
  "compliment_more": 0,
  "elite": [],
  "compliment_hot": 0,
  "cool": 0,
  "name": "Catrina",
  "compliment_profile": 0,
  "compliment_cool": 0
}, {
  "yelping_since": "2015-08-05",
  "useful": 0,
  "compliment_photos": 0,
  "compliment_list": 0,
  "compliment_funny": 0,
  "funny": 0,
  "review_count": 7,
  "friends": [],
  "fans": 0,
  "compliment_note": 0,
  "compliment_plain": 0,
  "compliment_writer": 0,
  "compliment_cute": 0,
  "average_stars": 2.86,
  "user_id": "zfDcvo9F7d9fAA_hWcBC5Q",
  "compliment_more": 0,
  "elite": [],
  "compliment_hot": 0,
  "cool": 0,
  "name": "Mela",
  "compliment_profile": 0,
  "compliment_cool": 0
}, {
  "yelping_since": "2015-04-22",
  "useful": 1,
  "compliment_photos": 0,
  "compliment_list": 0,
  "compliment_funny": 0,
  "funny": 0,
  "review_count": 2,
  "friends": [],
  "fans": 0,
  "compliment_note": 0,
  "compliment_plain": 0,
  "compliment_writer": 0,
  "compliment_cute": 0,
  "average_stars": 4.0,
  "user_id": "hpG8FtZgiroAk45t0iGIoA",
  "compliment_more": 0,
  "elite": [],
  "compliment_hot": 0,
  "cool": 0,
  "name": "Katherine",
  "compliment_profile": 0,
  "compliment_cool": 0
}, {
  "yelping_since": "2014-01-08",
  "useful": 0,
  "compliment_photos": 0,
  "compliment_list": 0,
  "compliment_funny": 0,
  "funny": 0,
  "review_count": 2,
  "friends": [],
  "fans": 0,
  "compliment_note": 0,
  "compliment_plain": 0,
  "compliment_writer": 0,
  "compliment_cute": 0,
  "average_stars": 3.0,
  "user_id": "ioGZM2EjWbtd8vt__ZHicg",
  "compliment_more": 0,
  "elite": [],
  "compliment_hot": 0,
  "cool": 0,
  "name": "Val",
  "compliment_profile": 0,
  "compliment_cool": 0
}, {
  "yelping_since": "2017-11-16",
  "useful": 0,
  "compliment_photos": 0,
  "compliment_list": 0,
  "compliment_funny": 0,
  "funny": 0,
  "review_count": 1,
  "friends": [],
  "fans": 0,
  "compliment_note": 0,
  "compliment_plain": 0,
  "compliment_writer": 0,
  "compliment_cute": 0,
  "average_stars": 5.0,
  "user_id": "c7NwhrSXaWqnIRdIByWyAA",
  "compliment_more": 0,
  "elite": [],
  "compliment_hot": 0,
  "cool": 0,
  "name": "Tim",
  "compliment_profile": 0,
  "compliment_cool": 0
}, {
  "yelping_since": "2010-04-23",
  "useful": 0,
  "compliment_photos": 0,
  "compliment_list": 0,
  "compliment_funny": 0,
  "funny": 0,
  "review_count": 1,
  "friends": [],
  "fans": 0,
  "compliment_note": 0,
  "compliment_plain": 0,
  "compliment_writer": 0,
  "compliment_cute": 0,
  "average_stars": 2.0,
  "user_id": "HQpUPfZOZseRKl2gLol23w",
  "compliment_more": 0,
  "elite": [],
  "compliment_hot": 0,
  "cool": 0,
  "name": "openspe",
  "compliment_profile": 0,
  "compliment_cool": 0
}, {
  "yelping_since": "2010-03-24",
  "useful": 1,
  "compliment_photos": 0,
  "compliment_list": 0,
  "compliment_funny": 0,
  "funny": 0,
  "review_count": 11,
  "friends": [],
  "fans": 0,
  "compliment_note": 1,
  "compliment_plain": 0,
  "compliment_writer": 0,
  "compliment_cute": 0,
  "average_stars": 4.38,
  "user_id": "4W9XxyGSHXUlAIfJ2ySBIQ",
  "compliment_more": 0,
  "elite": [],
  "compliment_hot": 0,
  "cool": 0,
  "name": "JR",
  "compliment_profile": 0,
  "compliment_cool": 0
}]
